[{"node":{"alternateId":12277,"campaign":null,"clientBudget":3,"employeeRangeId":2,"id":"5b538a7f-0eb7-bb80-fc8b-6a65e18e8662","industries":["Accounting","Construction","Entertainment","Health, Wellness and Fitness","Hospital & Health Care","Hospitality","Individual & Family Services","Industrial Automation","Information Services","Medical Practice","Real Estate","Restaurants","Retail"],"insights":{"projectCost":[{"docCount":3,"key":"total"},{"docCount":2,"key":"Unspecified"},{"docCount":1,"key":"B"}],"projectMonthlyCost":[{"docCount":3,"key":"total"},{"docCount":2,"key":"Unspecified"},{"docCount":1,"key":"D"}],"reviewerCompanySize":[{"docCount":3,"key":"total"},{"docCount":3,"key":"Unspecified"}],"reviewerIndustry":[{"docCount":1,"key":"total"},{"docCount":1,"key":"real_estate"}]},"logoUrl":"https://s3.amazonaws.com/top-local-agencies/profiles/logos/000/002/223/original/Arise-Logo-2016-solid.png","name":"Arise Design","physicalLocations":[{"city":"San Diego","countryCode":"US","id":"b252b1b7-da23-47ea-9ca7-0d72510a82ed","state":"California"}],"primaryLocation":{"city":"San Diego","countryCode":"US","id":"b252b1b7-da23-47ea-9ca7-0d72510a82ed","state":"California"},"projectBasedBudget":null,"reviewSummary":{"rating":{"rating":0.73},"totalCount":3},"services":[{"id":"advertising","name":"Advertising"},{"id":"branding","name":"Branding"},{"id":"creative","name":"Creative"},{"id":"design","name":"Design"},{"id":"digital-marketing","name":"Digital Marketing"},{"id":"full-service-digital","name":"Full Service Digital"},{"id":"graphic-design","name":"Graphic Design"},{"id":"marketing-analytics","name":"Marketing Analytics"},{"id":"public-relations-pr","name":"Public Relations (PR)"},{"id":"seo","name":"SEO"},{"id":"social-media-marketing","name":"Social Media Marketing"},{"id":"web-design","name":"Web Design"},{"id":"web-development","name":"Web Development"}],"slug":"arise-design","tagline":"California-based branding, web design and marketing firm","technologies":[],"verified":true,"websiteUrl":"https://www.arisedesigngroup.com","yearFounded":2023}},{"node":{"alternateId":9266,"campaign":null,"clientBudget":4,"employeeRangeId":2,"id":"0344803c-5a98-33cf-5db1-e508a58a7c8f","industries":["Information Services","Information Technology and Services"],"insights":{"projectCost":[{"docCount":3,"key":"total"},{"docCount":3,"key":"Unspecified"}],"projectMonthlyCost":[{"docCount":3,"key":"total"},{"docCount":3,"key":"Unspecified"}],"reviewerCompanySize":[{"docCount":3,"key":"total"},{"docCount":3,"key":"Unspecified"}],"reviewerIndustry":[{"docCount":0,"key":"total"}]},"logoUrl":"https://s3.amazonaws.com/top-local-agencies/profiles/logos/000/002/478/original/facebook1.png","name":"GVATE LLC","physicalLocations":[{"city":"New York","countryCode":"US","id":"984386c9-9a9c-445a-a516-a7c85aaeac4f","state":"New York"}],"primaryLocation":{"city":"New York","countryCode":"US","id":"984386c9-9a9c-445a-a516-a7c85aaeac4f","state":"New York"},"projectBasedBudget":3,"reviewSummary":{"rating":{"rating":0.6},"totalCount":3},"services":[{"id":"advertising","name":"Advertising"},{"id":"digital-marketing","name":"Digital Marketing"},{"id":"full-service-digital","name":"Full Service Digital"},{"id":"marketing-analytics","name":"Marketing Analytics"},{"id":"seo","name":"SEO"},{"id":"social-media-marketing","name":"Social Media Marketing"},{"id":"web-design","name":"Web Design"},{"id":"web-development","name":"Web Development"}],"slug":"gvate-llc","tagline":"Award-winning SEO and PPC service company based in NYC","technologies":[],"verified":true,"websiteUrl":"https://www.gvate.com","yearFounded":2015}},{"node":{"alternateId":5708,"campaign":null,"clientBudget":2,"employeeRangeId":4,"id":"8880971b-e7e7-a298-d196-6f4ff2e61a40","industries":["Construction","Consumer Services","Individual & Family Services","Information Services","Real Estate","Think Tanks"],"insights":{"projectCost":[{"docCount":3,"key":"total"},{"docCount":2,"key":"A"},{"docCount":1,"key":"G"}],"projectMonthlyCost":[{"docCount":3,"key":"total"},{"docCount":1,"key":"B"},{"docCount":2,"key":"A"}],"reviewerCompanySize":[{"docCount":3,"key":"total"},{"docCount":2,"key":"Unspecified"},{"docCount":1,"key":"F"}],"reviewerIndustry":[{"docCount":2,"key":"total"},{"docCount":2,"key":"real_estate"}]},"logoUrl":"https://s3.amazonaws.com/top-local-agencies/profiles/logos/000/140/375/original/tpr-logo-1.png","name":"Top Page Rankers","physicalLocations":[{"city":"Lauderhill","countryCode":"US","id":"7301ea77-3f8c-4473-a107-7c38956e71c2","state":"Florida"}],"primaryLocation":{"city":"Lauderhill","countryCode":"US","id":"7301ea77-3f8c-4473-a107-7c38956e71c2","state":"Florida"},"projectBasedBudget":2,"reviewSummary":{"rating":{"rating":0.47},"totalCount":3},"services":[{"id":"artificial-intelligence","name":"Artificial Intelligence"},{"id":"branding","name":"Branding"},{"id":"digital-marketing","name":"Digital Marketing"},{"id":"mobile-app-development","name":"Mobile App Development"},{"id":"social-media-marketing","name":"Social Media Marketing"},{"id":"web-design","name":"Web Design"},{"id":"web-development","name":"Web Development"}],"slug":"top-page-rankers","tagline":"Digital marketing agency headquartered in Houston","technologies":[],"verified":true,"websiteUrl":"https://toppagerankers.com","yearFounded":2014}},{"node":{"alternateId":2736319,"campaign":null,"clientBudget":2,"employeeRangeId":2,"id":"fe031cd9-8905-4c49-8d3c-907e0c42d606","industries":["Accounting","Automotive","Construction","Consumer Services","Entertainment","Food & Beverages","Health, Wellness and Fitness","Hospitality","Information Services"],"insights":{"projectCost":[{"docCount":2,"key":"total"},{"docCount":2,"key":"A"}],"projectMonthlyCost":[{"docCount":2,"key":"total"},{"docCount":2,"key":"A"}],"reviewerCompanySize":[{"docCount":2,"key":"total"},{"docCount":2,"key":"Unspecified"}],"reviewerIndustry":[{"docCount":2,"key":"total"},{"docCount":1,"key":"health"},{"docCount":1,"key":"retail"}]},"logoUrl":"https://s3.amazonaws.com/top-local-agencies/profiles/logos/000/314/931/original/WDG_LOGO.png","name":"Web Design Glory","physicalLocations":[{"city":"Duluth","countryCode":"US","id":"18d181ec-f7bc-4abc-96af-47ccd21ab762","state":"Georgia"}],"primaryLocation":{"city":"Duluth","countryCode":"US","id":"18d181ec-f7bc-4abc-96af-47ccd21ab762","state":"Georgia"},"projectBasedBudget":1,"reviewSummary":{"rating":{"rating":1},"totalCount":2},"services":[{"id":"branding","name":"Branding"},{"id":"digital-marketing","name":"Digital Marketing"},{"id":"mobile-app-development","name":"Mobile App Development"},{"id":"user-experience-design","name":"User Experience Design"},{"id":"video-production","name":"Video Production"},{"id":"web-design","name":"Web Design"},{"id":"web-development","name":"Web Development"}],"slug":"web-design-glory","tagline":"Elevate your online presence with Web Design Glory!","technologies":[],"verified":true,"websiteUrl":"https://www.webdesignglory.com","yearFounded":2016}},{"node":{"alternateId":17213,"campaign":null,"clientBudget":5,"employeeRangeId":2,"id":"5da23d16-0546-5166-81e7-bd7ff8e9502b","industries":["Accounting","Automotive","Financial Services","Health, Wellness and Fitness","Hospital & Health Care","Hospitality","Industrial Automation","Information Services","Information Technology and Services","Oil & Energy","Professional Training & Coaching","Think Tanks"],"insights":{"projectCost":[{"docCount":2,"key":"total"},{"docCount":2,"key":"G"}],"projectMonthlyCost":[{"docCount":2,"key":"total"},{"docCount":2,"key":"E"}],"reviewerCompanySize":[{"docCount":2,"key":"total"},{"docCount":2,"key":"Unspecified"}],"reviewerIndustry":[{"docCount":0,"key":"total"}]},"logoUrl":"https://s3.amazonaws.com/top-local-agencies/profiles/logos/000/025/426/original/MM_Logo_Blue_medium.png","name":"Marsden Marketing","physicalLocations":[{"city":"Atlanta","countryCode":"US","id":"58e3351f-7ac1-465d-bb8c-013226ad26df","state":"Georgia"}],"primaryLocation":{"city":"Atlanta","countryCode":"US","id":"58e3351f-7ac1-465d-bb8c-013226ad26df","state":"Georgia"},"projectBasedBudget":5,"reviewSummary":{"rating":{"rating":1},"totalCount":2},"services":[{"id":"advertising","name":"Advertising"},{"id":"branding","name":"Branding"},{"id":"content-marketing","name":"Content Marketing"},{"id":"digital-marketing","name":"Digital Marketing"},{"id":"email-marketing","name":"Email Marketing"},{"id":"full-service-digital","name":"Full Service Digital"},{"id":"lead-generation","name":"Lead Generation"},{"id":"ppc","name":"PPC"},{"id":"public-relations-pr","name":"Public Relations (PR)"},{"id":"seo","name":"SEO"},{"id":"social-media-marketing","name":"Social Media Marketing"},{"id":"video-production","name":"Video Production"},{"id":"web-design","name":"Web Design"},{"id":"web-development","name":"Web Development"}],"slug":"marsden-marketing","tagline":"Atlanta-based B2B marketing agency specializing in digital marketing, demand generation, strategy, and PR.","technologies":[],"verified":true,"websiteUrl":"https://www.marsdenmarketing.com","yearFounded":2023}},{"node":{"alternateId":10579,"campaign":null,"clientBudget":1,"employeeRangeId":1,"id":"ac44332b-9a68-a19a-fb74-879ffec1d59f","industries":["Consumer Services","Food & Beverages","Hospitality","Information Services","Non-Profit Organization Management","Think Tanks"],"insights":{"projectCost":[{"docCount":2,"key":"total"},{"docCount":1,"key":"G"},{"docCount":1,"key":"A"}],"projectMonthlyCost":[{"docCount":2,"key":"total"},{"docCount":1,"key":"A"},{"docCount":1,"key":"F"}],"reviewerCompanySize":[{"docCount":2,"key":"total"},{"docCount":2,"key":"Unspecified"}],"reviewerIndustry":[{"docCount":2,"key":"total"},{"docCount":2,"key":"public"}]},"logoUrl":"https://s3.amazonaws.com/top-local-agencies/profiles/logos/000/185/650/original/Upsway_(10).png","name":"Upsway Marketing","physicalLocations":[{"city":"Atlanta","countryCode":"US","id":"58e3351f-7ac1-465d-bb8c-013226ad26df","state":"Georgia"}],"primaryLocation":{"city":"Atlanta","countryCode":"US","id":"58e3351f-7ac1-465d-bb8c-013226ad26df","state":"Georgia"},"projectBasedBudget":1,"reviewSummary":{"rating":{"rating":1},"totalCount":2},"services":[{"id":"branding","name":"Branding"},{"id":"digital-marketing","name":"Digital Marketing"},{"id":"full-service-digital","name":"Full Service Digital"},{"id":"seo","name":"SEO"},{"id":"social-media-marketing","name":"Social Media Marketing"},{"id":"web-design","name":"Web Design"}],"slug":"upsway-marketing","tagline":"Digital marketing for small businesses and startups","technologies":[],"verified":true,"websiteUrl":"https://www.upswaymarketing.com","yearFounded":2020}},{"node":{"alternateId":975044,"campaign":null,"clientBudget":null,"employeeRangeId":null,"id":"8e94091c-fa56-4512-aac3-da0a6c1eabaa","industries":[],"insights":{"projectCost":[{"docCount":2,"key":"total"},{"docCount":2,"key":"B"}],"projectMonthlyCost":[{"docCount":2,"key":"total"},{"docCount":1,"key":"C"},{"docCount":1,"key":"E"}],"reviewerCompanySize":[{"docCount":2,"key":"total"},{"docCount":1,"key":"B"},{"docCount":1,"key":"Unspecified"}],"reviewerIndustry":[{"docCount":2,"key":"total"},{"docCount":1,"key":"finance"},{"docCount":1,"key":"it"}]},"logoUrl":"https://s3.amazonaws.com/top-local-agencies/profiles/logos/000/313/251/original/ITAdviser.png","name":"itAdviser","physicalLocations":[],"primaryLocation":null,"projectBasedBudget":null,"reviewSummary":{"rating":{"rating":1},"totalCount":2},"services":[{"id":"custom-software-development","name":"Custom Software Development"},{"id":"digital-marketing","name":"Digital Marketing"},{"id":"it-services","name":"IT Services"},{"id":"mobile-app-development","name":"Mobile App Development"},{"id":"web-design","name":"Web Design"},{"id":"web-development","name":"Web Development"}],"slug":"itadviser","tagline":"IT Research and Development Company","technologies":[],"verified":true,"websiteUrl":"https://itadviser.dev","yearFounded":2010}},{"node":{"alternateId":64535,"campaign":null,"clientBudget":6,"employeeRangeId":2,"id":"5753d9df-9588-4545-a202-c78f8631b112","industries":["Accounting","Construction","Education Management","Hospital & Health Care","Hospitality","Information Technology and Services","Real Estate","Think Tanks"],"insights":{"projectCost":[{"docCount":2,"key":"total"},{"docCount":1,"key":"B"},{"docCount":1,"key":"G"}],"projectMonthlyCost":[{"docCount":2,"key":"total"},{"docCount":1,"key":"E"},{"docCount":1,"key":"F"}],"reviewerCompanySize":[{"docCount":2,"key":"total"},{"docCount":2,"key":"Unspecified"}],"reviewerIndustry":[{"docCount":2,"key":"total"},{"docCount":1,"key":"health"},{"docCount":1,"key":"professional"}]},"logoUrl":"https://s3.amazonaws.com/top-local-agencies/profiles/logos/000/312/518/original/new_logo.png","name":"Uitop","physicalLocations":[{"city":"New York","countryCode":"US","id":"984386c9-9a9c-445a-a516-a7c85aaeac4f","state":"New York"}],"primaryLocation":{"city":"New York","countryCode":"US","id":"984386c9-9a9c-445a-a516-a7c85aaeac4f","state":"New York"},"projectBasedBudget":5,"reviewSummary":{"rating":{"rating":1},"totalCount":2},"services":[{"id":"digital-marketing","name":"Digital Marketing"},{"id":"mobile-app-development","name":"Mobile App Development"},{"id":"user-experience-design","name":"User Experience Design"},{"id":"web-design","name":"Web Design"}],"slug":"uitop","tagline":"Website and mobile app development company based in New York","technologies":[],"verified":true,"websiteUrl":"https://uitop.design","yearFounded":2021}},{"node":{"alternateId":164691,"campaign":null,"clientBudget":3,"employeeRangeId":1,"id":"be127266-9d38-4531-82ce-c10c29843428","industries":["Health, Wellness and Fitness","Hospitality","Individual & Family Services","Information Services","Think Tanks"],"insights":{"projectCost":[{"docCount":2,"key":"total"},{"docCount":1,"key":"A"},{"docCount":1,"key":"G"}],"projectMonthlyCost":[{"docCount":2,"key":"total"},{"docCount":2,"key":"F"}],"reviewerCompanySize":[{"docCount":2,"key":"total"},{"docCount":2,"key":"Unspecified"}],"reviewerIndustry":[{"docCount":2,"key":"total"},{"docCount":1,"key":"health"},{"docCount":1,"key":"professional"}]},"logoUrl":"https://s3.amazonaws.com/top-local-agencies/profiles/logos/000/313/107/original/st49-submark-new-blk_transparent_png.png","name":"Studio Three 49 Digital Marketing","physicalLocations":[{"city":"Raleigh","countryCode":"US","id":"d2e694ee-eb21-46b3-b127-6f1706a1c47f","state":"North Carolina"}],"primaryLocation":{"city":"Raleigh","countryCode":"US","id":"d2e694ee-eb21-46b3-b127-6f1706a1c47f","state":"North Carolina"},"projectBasedBudget":2,"reviewSummary":{"rating":{"rating":1},"totalCount":2},"services":[{"id":"branding","name":"Branding"},{"id":"content-marketing","name":"Content Marketing"},{"id":"creative","name":"Creative"},{"id":"digital-marketing","name":"Digital Marketing"},{"id":"email-marketing","name":"Email Marketing"},{"id":"seo","name":"SEO"},{"id":"social-media-marketing","name":"Social Media Marketing"}],"slug":"studio-three-49-digital-marketing","tagline":"Smart digital marketing solutions for entrepreneurs and small businesses.","technologies":[],"verified":true,"websiteUrl":"https://www.studiothree49.com","yearFounded":2020}},{"node":{"alternateId":39940,"campaign":null,"clientBudget":3,"employeeRangeId":2,"id":"ad528b0d-6dc6-4d5f-be33-f61603e158fc","industries":["Construction","Consumer Services","Education Management","Industrial Automation","Information Services","Information Technology and Services","Retail","Think Tanks"],"insights":{"projectCost":[{"docCount":2,"key":"total"},{"docCount":2,"key":"B"}],"projectMonthlyCost":[{"docCount":2,"key":"total"},{"docCount":1,"key":"B"},{"docCount":1,"key":"C"}],"reviewerCompanySize":[{"docCount":2,"key":"total"},{"docCount":1,"key":"D"},{"docCount":1,"key":"Unspecified"}],"reviewerIndustry":[{"docCount":2,"key":"total"},{"docCount":1,"key":"professional"},{"docCount":1,"key":"transportation"}]},"logoUrl":"https://s3.amazonaws.com/top-local-agencies/profiles/logos/000/312/393/original/logo_black.png","name":"Marketing Link","physicalLocations":[{"city":"Fort Myers","countryCode":"US","id":"5da3b941-b5df-433b-a9ea-33e601bd7698","state":"Florida"}],"primaryLocation":{"city":"Fort Myers","countryCode":"US","id":"5da3b941-b5df-433b-a9ea-33e601bd7698","state":"Florida"},"projectBasedBudget":2,"reviewSummary":{"rating":{"rating":1},"totalCount":2},"services":[{"id":"advertising","name":"Advertising"},{"id":"digital-marketing","name":"Digital Marketing"},{"id":"email-marketing","name":"Email Marketing"},{"id":"ppc","name":"PPC"},{"id":"seo","name":"SEO"}],"slug":"marketing-link","tagline":"Digital marketing agency offering PPC and SEO service","technologies":[],"verified":true,"websiteUrl":"https://marketing.link","yearFounded":2016}},{"node":{"alternateId":121455,"campaign":null,"clientBudget":6,"employeeRangeId":2,"id":"893ea5f2-b97d-423e-a8f7-d7608f30762b","industries":["Accounting","Automotive","Construction","Consumer Services","Education Management","Entertainment","Food & Beverages","Health, Wellness and Fitness","Hospital & Health Care","Hospitality","Individual & Family Services","Industrial Automation","Information Services","Information Technology and Services","Law Practice","Leisure, Travel & Tourism","Medical Practice","Non-Profit Organization Management","Oil & Energy","Real Estate","Restaurants","Retail","Sports","Think Tanks"],"insights":{"projectCost":[{"docCount":2,"key":"total"},{"docCount":2,"key":"Unspecified"}],"projectMonthlyCost":[{"docCount":2,"key":"total"},{"docCount":2,"key":"Unspecified"}],"reviewerCompanySize":[{"docCount":2,"key":"total"},{"docCount":2,"key":"Unspecified"}],"reviewerIndustry":[{"docCount":1,"key":"total"},{"docCount":1,"key":"it"}]},"logoUrl":"https://s3.amazonaws.com/top-local-agencies/profiles/logos/000/312/845/original/novovision-logo.jpg","name":"NovoVision Agency","physicalLocations":[{"city":"Park City","countryCode":"US","id":"085d13d8-d158-4046-bd78-dad2e5dc4a50","state":"Utah"}],"primaryLocation":{"city":"Park City","countryCode":"US","id":"085d13d8-d158-4046-bd78-dad2e5dc4a50","state":"Utah"},"projectBasedBudget":6,"reviewSummary":{"rating":{"rating":1},"totalCount":2},"services":[{"id":"advertising","name":"Advertising"},{"id":"branding","name":"Branding"},{"id":"content-marketing","name":"Content Marketing"},{"id":"creative","name":"Creative"},{"id":"digital-marketing","name":"Digital Marketing"},{"id":"email-marketing","name":"Email Marketing"},{"id":"graphic-design","name":"Graphic Design"},{"id":"logo-design","name":"Logo Design"},{"id":"mobile-app-development","name":"Mobile App Development"},{"id":"ppc","name":"PPC"},{"id":"seo","name":"SEO"},{"id":"social-media-marketing","name":"Social Media Marketing"},{"id":"user-experience-design","name":"User Experience Design"},{"id":"web-design","name":"Web Design"},{"id":"web-development","name":"Web Development"}],"slug":"novovision-agency","tagline":"Digital agency offering digital marketing, SEO & brand strategy","technologies":[],"verified":true,"websiteUrl":"https://novovisionagency.com","yearFounded":2019}},{"node":{"alternateId":38620,"campaign":null,"clientBudget":6,"employeeRangeId":4,"id":"09ece701-9da3-4cce-893b-923ad931fb42","industries":["Accounting","Consumer Services","Education Management","Government Administration","Hospital & Health Care","Hospitality","Real Estate","Retail"],"insights":{"projectCost":[{"docCount":2,"key":"total"},{"docCount":1,"key":"B"},{"docCount":1,"key":"G"}],"projectMonthlyCost":[{"docCount":2,"key":"total"},{"docCount":2,"key":"Unspecified"}],"reviewerCompanySize":[{"docCount":2,"key":"total"},{"docCount":2,"key":"Unspecified"}],"reviewerIndustry":[{"docCount":2,"key":"total"},{"docCount":2,"key":"health"}]},"logoUrl":"https://s3.amazonaws.com/top-local-agencies/profiles/logos/000/292/574/original/digitrends-logo.jpg","name":"DigiTrends","physicalLocations":[{"city":"San Francisco","countryCode":"US","id":"1994622d-5594-4fc1-a444-3a52644d937b","state":"California"}],"primaryLocation":{"city":"San Francisco","countryCode":"US","id":"1994622d-5594-4fc1-a444-3a52644d937b","state":"California"},"projectBasedBudget":4,"reviewSummary":{"rating":{"rating":1},"totalCount":2},"services":[{"id":"artificial-intelligence","name":"Artificial Intelligence"},{"id":"custom-software-development","name":"Custom Software Development"},{"id":"digital-marketing","name":"Digital Marketing"},{"id":"full-service-digital","name":"Full Service Digital"},{"id":"machine-learning","name":"Machine Learning"},{"id":"mobile-app-development","name":"Mobile App Development"},{"id":"seo","name":"SEO"},{"id":"social-media-marketing","name":"Social Media Marketing"},{"id":"user-experience-design","name":"User Experience Design"},{"id":"web-design","name":"Web Design"},{"id":"web-development","name":"Web Development"}],"slug":"digitrends","tagline":"Full-stack app development and branding agency","technologies":[],"verified":true,"websiteUrl":"https://digitrends.co","yearFounded":2010}},{"node":{"alternateId":3287,"campaign":null,"clientBudget":1,"employeeRangeId":2,"id":"67b13888-fefa-f5a0-3b97-bb0fb4cd5f07","industries":["Food & Beverages","Industrial Automation","Information Services","Restaurants","Retail"],"insights":{"projectCost":[{"docCount":2,"key":"total"},{"docCount":1,"key":"G"},{"docCount":1,"key":"A"}],"projectMonthlyCost":[{"docCount":2,"key":"total"},{"docCount":1,"key":"F"},{"docCount":1,"key":"Unspecified"}],"reviewerCompanySize":[{"docCount":2,"key":"total"},{"docCount":2,"key":"Unspecified"}],"reviewerIndustry":[{"docCount":1,"key":"total"},{"docCount":1,"key":"retail"}]},"logoUrl":"https://s3.amazonaws.com/top-local-agencies/profiles/logos/000/182/312/original/open-uri20211020-18099-1c7v4qd","name":"Fancy Clam","physicalLocations":[{"city":"Saint Paul","countryCode":"US","id":"90a239a6-fe01-4c38-a230-4634504a44cd","state":"Minnesota"}],"primaryLocation":{"city":"Saint Paul","countryCode":"US","id":"90a239a6-fe01-4c38-a230-4634504a44cd","state":"Minnesota"},"projectBasedBudget":1,"reviewSummary":{"rating":{"rating":1},"totalCount":2},"services":[{"id":"advertising","name":"Advertising"},{"id":"digital-marketing","name":"Digital Marketing"},{"id":"email-marketing","name":"Email Marketing"},{"id":"ppc","name":"PPC"},{"id":"seo","name":"SEO"},{"id":"video-production","name":"Video Production"},{"id":"web-design","name":"Web Design"},{"id":"web-development","name":"Web Development"}],"slug":"fancy-clam","tagline":"Digital marketing and web design agency based in Minnesota","technologies":[],"verified":true,"websiteUrl":"https://www.fancyclam.com","yearFounded":2016}},{"node":{"alternateId":2438,"campaign":null,"clientBudget":1,"employeeRangeId":2,"id":"3bfca473-0f90-8a02-49e3-f530fb4b8ec7","industries":["Automotive","Consumer Services","Education Management","Industrial Automation","Restaurants","Think Tanks"],"insights":{"projectCost":[{"docCount":2,"key":"total"},{"docCount":2,"key":"A"}],"projectMonthlyCost":[{"docCount":2,"key":"total"},{"docCount":1,"key":"A"},{"docCount":1,"key":"Unspecified"}],"reviewerCompanySize":[{"docCount":2,"key":"total"},{"docCount":2,"key":"Unspecified"}],"reviewerIndustry":[{"docCount":2,"key":"total"},{"docCount":1,"key":"retail"},{"docCount":1,"key":"transportation"}]},"logoUrl":"https://s3.amazonaws.com/top-local-agencies/profiles/logos/000/113/587/original/WB12.png","name":"WEB BONAFIDE","physicalLocations":[{"city":"Houston","countryCode":"US","id":"fda47ce0-cff4-479c-8d2c-dce929da3c9b","state":"Texas"}],"primaryLocation":{"city":"Houston","countryCode":"US","id":"fda47ce0-cff4-479c-8d2c-dce929da3c9b","state":"Texas"},"projectBasedBudget":1,"reviewSummary":{"rating":{"rating":1},"totalCount":2},"services":[{"id":"advertising","name":"Advertising"},{"id":"branding","name":"Branding"},{"id":"digital-marketing","name":"Digital Marketing"},{"id":"full-service-digital","name":"Full Service Digital"},{"id":"seo","name":"SEO"},{"id":"social-media-marketing","name":"Social Media Marketing"},{"id":"web-design","name":"Web Design"},{"id":"web-development","name":"Web Development"}],"slug":"web-bonafide","tagline":"Digital marketing and web development provider in Houston","technologies":[],"verified":true,"websiteUrl":"https://www.webbonafide.com","yearFounded":2013}},{"node":{"alternateId":39690,"campaign":null,"clientBudget":3,"employeeRangeId":1,"id":"5a0507ce-d71a-4be2-a348-d7ef7f8728dc","industries":[],"insights":{"projectCost":[{"docCount":2,"key":"total"},{"docCount":1,"key":"A"},{"docCount":1,"key":"G"}],"projectMonthlyCost":[{"docCount":2,"key":"total"},{"docCount":1,"key":"Unspecified"},{"docCount":1,"key":"F"}],"reviewerCompanySize":[{"docCount":2,"key":"total"},{"docCount":2,"key":"Unspecified"}],"reviewerIndustry":[{"docCount":2,"key":"total"},{"docCount":1,"key":"arts"},{"docCount":1,"key":"hospitality"}]},"logoUrl":"https://s3.amazonaws.com/top-local-agencies/profiles/logos/000/310/980/original/Screenshot_2023-01-31_at_5.40.12_PM.png","name":"On Target Marketing Solutions","physicalLocations":[{"city":"Chattanooga","countryCode":"US","id":"85dd162d-48ed-4d9c-9435-a436e0e9192e","state":"Tennessee"}],"primaryLocation":{"city":"Chattanooga","countryCode":"US","id":"85dd162d-48ed-4d9c-9435-a436e0e9192e","state":"Tennessee"},"projectBasedBudget":1,"reviewSummary":{"rating":{"rating":1},"totalCount":2},"services":[{"id":"digital-marketing","name":"Digital Marketing"},{"id":"lead-generation","name":"Lead Generation"},{"id":"ppc","name":"PPC"},{"id":"seo","name":"SEO"},{"id":"social-media-marketing","name":"Social Media Marketing"},{"id":"web-design","name":"Web Design"},{"id":"web-development","name":"Web Development"}],"slug":"on-target-marketing-solutions","tagline":"Lead generation and digital marketing strategy agency","technologies":[],"verified":true,"websiteUrl":"https://www.imontarget.com","yearFounded":2021}},{"node":{"alternateId":15167,"campaign":null,"clientBudget":5,"employeeRangeId":2,"id":"44abee53-685a-679d-2acd-915cfd08cc9d","industries":["Consumer Services","Information Services","Information Technology and Services"],"insights":{"projectCost":[{"docCount":2,"key":"total"},{"docCount":2,"key":"G"}],"projectMonthlyCost":[{"docCount":2,"key":"total"},{"docCount":2,"key":"F"}],"reviewerCompanySize":[{"docCount":2,"key":"total"},{"docCount":1,"key":"D"},{"docCount":1,"key":"Unspecified"}],"reviewerIndustry":[{"docCount":2,"key":"total"},{"docCount":1,"key":"real_estate"},{"docCount":1,"key":"retail"}]},"logoUrl":"https://s3.amazonaws.com/top-local-agencies/profiles/logos/000/070/685/original/DNSnetworks_ottawa_cybersecurity_services_and_managed_IT_services_logo.jpg","name":"DNSnetworks Corporation","physicalLocations":[{"city":"Ottawa","countryCode":"CA","id":"4041dc75-9938-4eeb-829c-ace1a2542153","state":"Ontario"}],"primaryLocation":{"city":"Ottawa","countryCode":"CA","id":"4041dc75-9938-4eeb-829c-ace1a2542153","state":"Ontario"},"projectBasedBudget":6,"reviewSummary":{"rating":{"rating":1},"totalCount":2},"services":[{"id":"artificial-intelligence","name":"Artificial Intelligence"},{"id":"digital-marketing","name":"Digital Marketing"},{"id":"managed-service-providers","name":"Managed Service Providers"},{"id":"web-design","name":"Web Design"},{"id":"web-development","name":"Web Development"}],"slug":"dnsnetworks-corporation","tagline":"Accelerate innovation while embracing digital disruption","technologies":[],"verified":true,"websiteUrl":"https://dnsnetworks.com","yearFounded":2003}},{"node":{"alternateId":14724,"campaign":null,"clientBudget":2,"employeeRangeId":2,"id":"e1df550a-a481-d6b7-6446-17cf72498482","industries":["Accounting","Consumer Services","Education Management","Entertainment","Hospitality","Information Services"],"insights":{"projectCost":[{"docCount":2,"key":"total"},{"docCount":1,"key":"B"},{"docCount":1,"key":"A"}],"projectMonthlyCost":[{"docCount":2,"key":"total"},{"docCount":1,"key":"D"},{"docCount":1,"key":"E"}],"reviewerCompanySize":[{"docCount":2,"key":"total"},{"docCount":1,"key":"Unspecified"},{"docCount":1,"key":"G"}],"reviewerIndustry":[{"docCount":2,"key":"total"},{"docCount":1,"key":"it"},{"docCount":1,"key":"real_estate"}]},"logoUrl":"https://s3.amazonaws.com/top-local-agencies/profiles/logos/000/002/457/original/new_vizion_site-logo.png","name":"Vizion Interactive","physicalLocations":[{"city":"Irving","countryCode":"US","id":"dbfe020a-d2f5-4915-993e-f326ae599a7f","state":"Texas"},{"city":"Overland Park","countryCode":"US","id":"5019f7d3-e0b7-481c-a485-ef1f87e987f1","state":"Kansas"},{"city":"Kansas City","countryCode":"US","id":"30f036ba-f3df-4ec3-a0b1-f01bc2af26fc","state":"Missouri"}],"primaryLocation":{"city":"Irving","countryCode":"US","id":"dbfe020a-d2f5-4915-993e-f326ae599a7f","state":"Texas"},"projectBasedBudget":2,"reviewSummary":{"rating":{"rating":1},"totalCount":2},"services":[{"id":"digital-marketing","name":"Digital Marketing"},{"id":"seo","name":"SEO"},{"id":"web-design","name":"Web Design"}],"slug":"vizion-interactive","tagline":"Full-service digital advertising agency with industry knowledge in e-commerce, B2B, industrial and more.","technologies":[],"verified":true,"websiteUrl":"https://www.vizion.com","yearFounded":2005}},{"node":{"alternateId":8190,"campaign":null,"clientBudget":1,"employeeRangeId":2,"id":"d2973923-35ee-523c-9ec9-b21dc6a2ed48","industries":["Consumer Services","Food & Beverages","Information Services","Information Technology and Services","Retail"],"insights":{"projectCost":[{"docCount":2,"key":"total"},{"docCount":1,"key":"A"},{"docCount":1,"key":"B"}],"projectMonthlyCost":[{"docCount":2,"key":"total"},{"docCount":1,"key":"D"},{"docCount":1,"key":"C"}],"reviewerCompanySize":[{"docCount":2,"key":"total"},{"docCount":1,"key":"D"},{"docCount":1,"key":"Unspecified"}],"reviewerIndustry":[{"docCount":2,"key":"total"},{"docCount":1,"key":"hospitality"},{"docCount":1,"key":"retail"}]},"logoUrl":"https://s3.amazonaws.com/top-local-agencies/profiles/logos/000/068/524/original/20210621-duco-displaypic-v1.jpg","name":"Duco Media","physicalLocations":[{"city":"Ottawa","countryCode":"CA","id":"4041dc75-9938-4eeb-829c-ace1a2542153","state":"Ontario"}],"primaryLocation":{"city":"Ottawa","countryCode":"CA","id":"4041dc75-9938-4eeb-829c-ace1a2542153","state":"Ontario"},"projectBasedBudget":1,"reviewSummary":{"rating":{"rating":1},"totalCount":2},"services":[{"id":"advertising","name":"Advertising"},{"id":"branding","name":"Branding"},{"id":"creative","name":"Creative"},{"id":"digital-marketing","name":"Digital Marketing"},{"id":"video-production","name":"Video Production"},{"id":"web-design","name":"Web Design"}],"slug":"duco-media","tagline":"Ottawa-based digital marketing and creative branding agency","technologies":[],"verified":true,"websiteUrl":"https://www.ducomedia.ca","yearFounded":2016}},{"node":{"alternateId":8347,"campaign":null,"clientBudget":6,"employeeRangeId":2,"id":"21e8735f-89cb-6a98-8915-45bc1405c40f","industries":["Hospitality","Medical Practice","Non-Profit Organization Management","Think Tanks"],"insights":{"projectCost":[{"docCount":2,"key":"total"},{"docCount":1,"key":"G"},{"docCount":1,"key":"A"}],"projectMonthlyCost":[{"docCount":2,"key":"total"},{"docCount":1,"key":"F"},{"docCount":1,"key":"None"}],"reviewerCompanySize":[{"docCount":2,"key":"total"},{"docCount":1,"key":"C"},{"docCount":1,"key":"Unspecified"}],"reviewerIndustry":[{"docCount":2,"key":"total"},{"docCount":2,"key":"health"}]},"logoUrl":"https://s3.amazonaws.com/top-local-agencies/profiles/logos/000/287/373/original/Clinician.PNG","name":"Clinician Box","physicalLocations":[{"city":"Louisville","countryCode":"US","id":"8f42ff26-d571-41c7-a92e-21736cee1d87","state":"Kentucky"}],"primaryLocation":{"city":"Louisville","countryCode":"US","id":"8f42ff26-d571-41c7-a92e-21736cee1d87","state":"Kentucky"},"projectBasedBudget":1,"reviewSummary":{"rating":{"rating":1},"totalCount":2},"services":[{"id":"branding","name":"Branding"},{"id":"content-marketing","name":"Content Marketing"},{"id":"digital-marketing","name":"Digital Marketing"},{"id":"ppc","name":"PPC"},{"id":"seo","name":"SEO"},{"id":"web-design","name":"Web Design"}],"slug":"clinician-box","tagline":"Digital marketing services for healthcare businesses","technologies":[],"verified":true,"websiteUrl":"https://www.clinicianbox.com","yearFounded":2021}},{"node":{"alternateId":18958,"campaign":null,"clientBudget":1,"employeeRangeId":4,"id":"96afc37c-4266-fdc2-aebd-de1ec41aaf75","industries":["Automotive","Consumer Services","Hospitality","Individual & Family Services","Real Estate","Think Tanks"],"insights":{"projectCost":[{"docCount":2,"key":"total"},{"docCount":2,"key":"A"}],"projectMonthlyCost":[{"docCount":2,"key":"total"},{"docCount":1,"key":"A"},{"docCount":1,"key":"F"}],"reviewerCompanySize":[{"docCount":2,"key":"total"},{"docCount":2,"key":"Unspecified"}],"reviewerIndustry":[{"docCount":2,"key":"total"},{"docCount":1,"key":"education"},{"docCount":1,"key":"retail"}]},"logoUrl":"https://s3.amazonaws.com/top-local-agencies/profiles/logos/000/093/634/original/data","name":"SITE IT NOW","physicalLocations":[{"city":"Chicago","countryCode":"US","id":"28dcf9dc-ef3a-4b03-b05e-fc810a44efd8","state":"Illinois"}],"primaryLocation":{"city":"Chicago","countryCode":"US","id":"28dcf9dc-ef3a-4b03-b05e-fc810a44efd8","state":"Illinois"},"projectBasedBudget":2,"reviewSummary":{"rating":{"rating":1},"totalCount":2},"services":[{"id":"advertising","name":"Advertising"},{"id":"branding","name":"Branding"},{"id":"digital-marketing","name":"Digital Marketing"},{"id":"full-service-digital","name":"Full Service Digital"},{"id":"seo","name":"SEO"},{"id":"social-media-marketing","name":"Social Media Marketing"},{"id":"web-design","name":"Web Design"}],"slug":"site-it-now","tagline":"Web design and SEO company based in Chicago, Illinois","technologies":[],"verified":true,"websiteUrl":"https://www.siteitnow.com","yearFounded":2009}},{"node":{"alternateId":45752,"campaign":null,"clientBudget":3,"employeeRangeId":1,"id":"44e6c381-ffdf-40a9-b25b-4e39aeaac3fa","industries":["Hospitality","Information Services","Medical Practice","Non-Profit Organization Management","Real Estate","Think Tanks"],"insights":{"projectCost":[{"docCount":2,"key":"total"},{"docCount":2,"key":"A"}],"projectMonthlyCost":[{"docCount":2,"key":"total"},{"docCount":2,"key":"F"}],"reviewerCompanySize":[{"docCount":2,"key":"total"},{"docCount":2,"key":"D"}],"reviewerIndustry":[{"docCount":2,"key":"total"},{"docCount":1,"key":"education"},{"docCount":1,"key":"real_estate"}]},"logoUrl":"https://s3.amazonaws.com/top-local-agencies/profiles/logos/000/312/190/original/Decka_Logo_Square.png","name":"Decka Enterprises LLC","physicalLocations":[{"city":"Murrieta","countryCode":"US","id":"e0e081eb-89bb-4825-a5ae-0aa01808ccec","state":"California"}],"primaryLocation":{"city":null,"countryCode":"US","id":"b13f93d7-929f-43f4-8fb9-f0285f0c216d","state":null},"projectBasedBudget":2,"reviewSummary":{"rating":{"rating":1},"totalCount":2},"services":[{"id":"advertising","name":"Advertising"},{"id":"branding","name":"Branding"},{"id":"creative","name":"Creative"},{"id":"digital-marketing","name":"Digital Marketing"},{"id":"ppc","name":"PPC"},{"id":"seo","name":"SEO"},{"id":"social-media-marketing","name":"Social Media Marketing"},{"id":"web-design","name":"Web Design"}],"slug":"decka-enterprises-llc","tagline":"Digital marketing, SEO, and web design services provider","technologies":[],"verified":true,"websiteUrl":"https://deckaservices.com","yearFounded":2022}},{"node":{"alternateId":38296,"campaign":null,"clientBudget":2,"employeeRangeId":2,"id":"d6c5442b-fefd-48a0-86fd-e1495fcf9b64","industries":["Accounting","Automotive","Food & Beverages","Leisure, Travel & Tourism","Real Estate","Think Tanks"],"insights":{"projectCost":[{"docCount":2,"key":"total"},{"docCount":1,"key":"Unspecified"},{"docCount":1,"key":"B"}],"projectMonthlyCost":[{"docCount":2,"key":"total"},{"docCount":1,"key":"E"},{"docCount":1,"key":"Unspecified"}],"reviewerCompanySize":[{"docCount":2,"key":"total"},{"docCount":1,"key":"G"},{"docCount":1,"key":"Unspecified"}],"reviewerIndustry":[{"docCount":2,"key":"total"},{"docCount":2,"key":"retail"}]},"logoUrl":"https://s3.amazonaws.com/top-local-agencies/profiles/logos/000/312/056/original/CHANGES.png","name":"Changes Agency","physicalLocations":[{"city":"Vancouver","countryCode":"CA","id":"88897d69-f095-427b-b9fd-33ffc89938e8","state":"British Columbia"}],"primaryLocation":{"city":"Vancouver","countryCode":"CA","id":"88897d69-f095-427b-b9fd-33ffc89938e8","state":"British Columbia"},"projectBasedBudget":4,"reviewSummary":{"rating":{"rating":1},"totalCount":2},"services":[{"id":"branding","name":"Branding"},{"id":"digital-marketing","name":"Digital Marketing"},{"id":"ppc","name":"PPC"},{"id":"public-relations-pr","name":"Public Relations (PR)"},{"id":"seo","name":"SEO"},{"id":"social-media-marketing","name":"Social Media Marketing"},{"id":"web-design","name":"Web Design"},{"id":"web-development","name":"Web Development"}],"slug":"changes-agency","tagline":"Vancouver-based digital marketing agency","technologies":[],"verified":true,"websiteUrl":"https://changes.agency","yearFounded":2021}},{"node":{"alternateId":39215,"campaign":null,"clientBudget":3,"employeeRangeId":1,"id":"eaf94c20-d4cc-4b78-a085-a9c5eb7b6ca6","industries":["Construction","Health, Wellness and Fitness","Hospitality","Individual & Family Services","Medical Practice","Non-Profit Organization Management"],"insights":{"projectCost":[{"docCount":2,"key":"total"},{"docCount":1,"key":"A"},{"docCount":1,"key":"G"}],"projectMonthlyCost":[{"docCount":2,"key":"total"},{"docCount":1,"key":"C"},{"docCount":1,"key":"D"}],"reviewerCompanySize":[{"docCount":2,"key":"total"},{"docCount":1,"key":"Unspecified"},{"docCount":1,"key":"D"}],"reviewerIndustry":[{"docCount":0,"key":"total"}]},"logoUrl":"https://s3.amazonaws.com/top-local-agencies/profiles/logos/000/306/329/original/Screen_Shot_2022-11-29_at_12.07.15_PM.png","name":"ExcuseBuster SEO","physicalLocations":[{"city":"Spring","countryCode":"US","id":"3da58885-5596-4ae0-9e95-9d82644c14e1","state":"Texas"}],"primaryLocation":{"city":"Spring","countryCode":"US","id":"3da58885-5596-4ae0-9e95-9d82644c14e1","state":"Texas"},"projectBasedBudget":2,"reviewSummary":{"rating":{"rating":1},"totalCount":2},"services":[{"id":"advertising","name":"Advertising"},{"id":"branding","name":"Branding"},{"id":"digital-marketing","name":"Digital Marketing"},{"id":"marketing-analytics","name":"Marketing Analytics"},{"id":"ppc","name":"PPC"},{"id":"seo","name":"SEO"}],"slug":"excusebuster-seo","tagline":"Digital agency offering personalized SEO service","technologies":[],"verified":true,"websiteUrl":"https://excusebusterseo.com","yearFounded":2021}},{"node":{"alternateId":69,"campaign":null,"clientBudget":null,"employeeRangeId":6,"id":"6e423beb-1c3a-457f-b91e-a6d8d048d23a","industries":["Accounting","Automotive","Aviation & Aerospace","Banking","Business Supplies and Equipment","Consumer Services","Financial Services","Hospital & Health Care","Hospitality","Information Technology and Services","Logistics and Supply Chain","Medical Practice","Online Media","Printing","Retail","Venture Capital & Private Equity"],"insights":{"projectCost":[{"docCount":2,"key":"total"},{"docCount":2,"key":"A"}],"projectMonthlyCost":[{"docCount":2,"key":"total"},{"docCount":1,"key":"C"},{"docCount":1,"key":"Unspecified"}],"reviewerCompanySize":[{"docCount":2,"key":"total"},{"docCount":1,"key":"B"},{"docCount":1,"key":"A"}],"reviewerIndustry":[{"docCount":2,"key":"total"},{"docCount":2,"key":"finance"}]},"logoUrl":"https://gdm-catalog-fmapi-prod.imgix.net/ProviderLogo/1d3c10ab-7e3b-49ac-8fe9-47bedf576ecf.png","name":"Auxis","physicalLocations":[{"city":"Fort Lauderdale","countryCode":"US","id":"db5a34cd-b8fe-42ee-a517-88a35e353dd3","state":"Florida"}],"primaryLocation":{"city":"Fort Lauderdale","countryCode":"US","id":"db5a34cd-b8fe-42ee-a517-88a35e353dd3","state":"Florida"},"projectBasedBudget":null,"reviewSummary":{"rating":{"rating":1},"totalCount":2},"services":[{"id":"accounting","name":"Accounting"},{"id":"artificial-intelligence","name":"Artificial Intelligence"},{"id":"cloud-consulting","name":"Cloud Consulting"},{"id":"custom-software-development","name":"Custom Software Development"},{"id":"data-analytics","name":"Data Analytics"},{"id":"digital-marketing","name":"Digital Marketing"},{"id":"iaas","name":"IaaS"},{"id":"machine-learning","name":"Machine Learning"},{"id":"marketing-analytics","name":"Marketing Analytics"},{"id":"mobile-app-development","name":"Mobile App Development"},{"id":"payroll","name":"Payroll"},{"id":"web-development","name":"Web Development"}],"slug":"auxis","tagline":"Consulting & outsourcing firm for cloud accounting ","technologies":[],"verified":true,"websiteUrl":"https://www.auxis.com","yearFounded":1997}},{"node":{"alternateId":17165,"campaign":null,"clientBudget":1,"employeeRangeId":2,"id":"2d3e1f9d-6019-cae6-f63c-df8501ce8e22","industries":["Entertainment","Information Services","Restaurants","Retail","Sports"],"insights":{"projectCost":[{"docCount":2,"key":"total"},{"docCount":1,"key":"B"},{"docCount":1,"key":"A"}],"projectMonthlyCost":[{"docCount":2,"key":"total"},{"docCount":2,"key":"C"}],"reviewerCompanySize":[{"docCount":2,"key":"total"},{"docCount":1,"key":"Unspecified"},{"docCount":1,"key":"F"}],"reviewerIndustry":[{"docCount":2,"key":"total"},{"docCount":1,"key":"health"},{"docCount":1,"key":"it"}]},"logoUrl":"https://s3.amazonaws.com/top-local-agencies/profiles/logos/000/065/701/original/full_logo_copy.jpg","name":"Insurrection Digital","physicalLocations":[{"city":"Powhatan","countryCode":"US","id":"1e7d03d1-2ba5-468b-9ff2-607901a1aa8f","state":"Virginia"}],"primaryLocation":{"city":"Powhatan","countryCode":"US","id":"1e7d03d1-2ba5-468b-9ff2-607901a1aa8f","state":"Virginia"},"projectBasedBudget":1,"reviewSummary":{"rating":{"rating":1},"totalCount":2},"services":[{"id":"branding","name":"Branding"},{"id":"content-marketing","name":"Content Marketing"},{"id":"digital-marketing","name":"Digital Marketing"},{"id":"full-service-digital","name":"Full Service Digital"},{"id":"ppc","name":"PPC"},{"id":"seo","name":"SEO"},{"id":"social-media-marketing","name":"Social Media Marketing"},{"id":"web-design","name":"Web Design"},{"id":"web-development","name":"Web Development"}],"slug":"insurrection-digital","tagline":"Digital marketing and website design agency in Richmond","technologies":[],"verified":true,"websiteUrl":"https://insurrectiondigital.com","yearFounded":2013}}]