[{"node":{"alternateId":7641,"campaign":null,"clientBudget":2,"employeeRangeId":1,"id":"82d0a1e7-c7b0-ec1e-659b-bcc368571fbc","industries":["Consumer Services","Law Practice","Leisure, Travel & Tourism","Medical Practice","Real Estate","Think Tanks"],"insights":{"projectCost":[{"docCount":13,"key":"total"},{"docCount":1,"key":"Unspecified"},{"docCount":2,"key":"G"},{"docCount":3,"key":"B"},{"docCount":7,"key":"A"}],"projectMonthlyCost":[{"docCount":13,"key":"total"},{"docCount":4,"key":"F"},{"docCount":2,"key":"Unspecified"},{"docCount":5,"key":"B"},{"docCount":2,"key":"A"}],"reviewerCompanySize":[{"docCount":13,"key":"total"},{"docCount":4,"key":"D"},{"docCount":8,"key":"Unspecified"},{"docCount":1,"key":"G"}],"reviewerIndustry":[{"docCount":9,"key":"total"},{"docCount":1,"key":"arts"},{"docCount":1,"key":"construction"},{"docCount":1,"key":"finance"},{"docCount":2,"key":"health"},{"docCount":2,"key":"public"},{"docCount":1,"key":"real_estate"},{"docCount":1,"key":"retail"}]},"logoUrl":"https://s3.amazonaws.com/top-local-agencies/profiles/logos/000/113/677/original/2020_FSM_Large.png","name":"Fire Source Media","physicalLocations":[{"city":"Waco","countryCode":"US","id":"e16cc1e6-05cd-428a-9ab2-1dd40aebf9fc","state":"Texas"}],"primaryLocation":{"city":"Waco","countryCode":"US","id":"e16cc1e6-05cd-428a-9ab2-1dd40aebf9fc","state":"Texas"},"projectBasedBudget":2,"reviewSummary":{"rating":{"rating":1},"totalCount":13},"services":[{"id":"advertising","name":"Advertising"},{"id":"digital-marketing","name":"Digital Marketing"},{"id":"seo","name":"SEO"},{"id":"web-design","name":"Web Design"},{"id":"web-development","name":"Web Development"}],"slug":"fire-source-media","tagline":"Digital marketing agency specializing in web development","technologies":[],"verified":true,"websiteUrl":"https://www.firesourcemedia.com","yearFounded":2012}},{"node":{"alternateId":9439,"campaign":null,"clientBudget":5,"employeeRangeId":4,"id":"be454c3f-012b-5b52-3910-42b55f248836","industries":["Accounting","Hospital & Health Care","Hospitality","Information Services","Real Estate","Retail"],"insights":{"projectCost":[{"docCount":13,"key":"total"},{"docCount":3,"key":"A"},{"docCount":2,"key":"B"},{"docCount":5,"key":"Unspecified"},{"docCount":3,"key":"G"}],"projectMonthlyCost":[{"docCount":13,"key":"total"},{"docCount":1,"key":"D"},{"docCount":1,"key":"B"},{"docCount":4,"key":"Unspecified"},{"docCount":3,"key":"E"},{"docCount":4,"key":"F"}],"reviewerCompanySize":[{"docCount":13,"key":"total"},{"docCount":3,"key":"D"},{"docCount":5,"key":"Unspecified"},{"docCount":3,"key":"G"},{"docCount":2,"key":"F"}],"reviewerIndustry":[{"docCount":6,"key":"total"},{"docCount":1,"key":"arts"},{"docCount":1,"key":"government"},{"docCount":1,"key":"health"},{"docCount":1,"key":"it"},{"docCount":1,"key":"retail"},{"docCount":1,"key":"utilities"}]},"logoUrl":"https://s3.amazonaws.com/top-local-agencies/profiles/logos/000/014/067/original/REQ-profile-facebook-180x180.png","name":"REQ","physicalLocations":[{"city":"Washington","countryCode":"US","id":"d22f7d86-0cc6-4a2f-bd82-4b8221225a7a","state":"District of Columbia"},{"city":"San Diego","countryCode":"US","id":"b252b1b7-da23-47ea-9ca7-0d72510a82ed","state":"California"},{"city":"Las Vegas","countryCode":"US","id":"ae87eca9-dd85-47ce-8079-8f08c943bf7c","state":"Nevada"}],"primaryLocation":{"city":"Washington","countryCode":"US","id":"d22f7d86-0cc6-4a2f-bd82-4b8221225a7a","state":"District of Columbia"},"projectBasedBudget":5,"reviewSummary":{"rating":{"rating":1},"totalCount":13},"services":[{"id":"advertising","name":"Advertising"},{"id":"branding","name":"Branding"},{"id":"content-marketing","name":"Content Marketing"},{"id":"design","name":"Design"},{"id":"digital-marketing","name":"Digital Marketing"},{"id":"graphic-design","name":"Graphic Design"},{"id":"marketing-analytics","name":"Marketing Analytics"},{"id":"public-relations-pr","name":"Public Relations (PR)"},{"id":"seo","name":"SEO"},{"id":"social-media-marketing","name":"Social Media Marketing"},{"id":"user-experience-design","name":"User Experience Design"},{"id":"web-design","name":"Web Design"}],"slug":"req","tagline":"Digital marketing and communications agency.","technologies":[],"verified":true,"websiteUrl":"https://req.co","yearFounded":2008}},{"node":{"alternateId":13823,"campaign":null,"clientBudget":6,"employeeRangeId":4,"id":"1676480a-eb10-5148-ab23-cd29ccf60344","industries":["Construction","Health, Wellness and Fitness","Individual & Family Services","Medical Practice","Restaurants","Retail"],"insights":{"projectCost":[{"docCount":13,"key":"total"},{"docCount":2,"key":"Unspecified"},{"docCount":4,"key":"G"},{"docCount":7,"key":"A"}],"projectMonthlyCost":[{"docCount":13,"key":"total"},{"docCount":1,"key":"E"},{"docCount":3,"key":"C"},{"docCount":3,"key":"F"},{"docCount":1,"key":"A"},{"docCount":2,"key":"B"},{"docCount":3,"key":"Unspecified"}],"reviewerCompanySize":[{"docCount":13,"key":"total"},{"docCount":1,"key":"F"},{"docCount":5,"key":"Unspecified"},{"docCount":7,"key":"D"}],"reviewerIndustry":[{"docCount":12,"key":"total"},{"docCount":2,"key":"construction"},{"docCount":8,"key":"health"},{"docCount":1,"key":"it"},{"docCount":1,"key":"real_estate"}]},"logoUrl":"https://s3.amazonaws.com/top-local-agencies/profiles/logos/000/030/062/original/DRlogo.jpg","name":"Digital Resource","physicalLocations":[{"city":"West Palm Beach","countryCode":"US","id":"1b83672e-6b11-4a49-bd76-7d47bb4341bf","state":"Florida"}],"primaryLocation":{"city":"West Palm Beach","countryCode":"US","id":"1b83672e-6b11-4a49-bd76-7d47bb4341bf","state":"Florida"},"projectBasedBudget":6,"reviewSummary":{"rating":{"rating":1},"totalCount":13},"services":[{"id":"advertising","name":"Advertising"},{"id":"content-marketing","name":"Content Marketing"},{"id":"digital-marketing","name":"Digital Marketing"},{"id":"email-marketing","name":"Email Marketing"},{"id":"full-service-digital","name":"Full Service Digital"},{"id":"graphic-design","name":"Graphic Design"},{"id":"public-relations-pr","name":"Public Relations (PR)"},{"id":"seo","name":"SEO"},{"id":"social-media-marketing","name":"Social Media Marketing"},{"id":"video-production","name":"Video Production"},{"id":"web-design","name":"Web Design"},{"id":"web-development","name":"Web Development"}],"slug":"digital-resource","tagline":"Full-service digital marketing agency in South Florida","technologies":[],"verified":true,"websiteUrl":"https://www.yourdigitalresource.com","yearFounded":2014}},{"node":{"alternateId":2862,"campaign":null,"clientBudget":2,"employeeRangeId":2,"id":"abd0acd7-dd96-28ca-8896-3a3f1dc8ae16","industries":["Automotive","Consumer Services","Information Services","Law Practice","Real Estate","Restaurants"],"insights":{"projectCost":[{"docCount":13,"key":"total"},{"docCount":5,"key":"A"},{"docCount":4,"key":"Unspecified"},{"docCount":4,"key":"B"}],"projectMonthlyCost":[{"docCount":13,"key":"total"},{"docCount":1,"key":"B"},{"docCount":5,"key":"Unspecified"},{"docCount":7,"key":"E"}],"reviewerCompanySize":[{"docCount":13,"key":"total"},{"docCount":10,"key":"Unspecified"},{"docCount":3,"key":"D"}],"reviewerIndustry":[{"docCount":9,"key":"total"},{"docCount":1,"key":"construction"},{"docCount":1,"key":"health"},{"docCount":1,"key":"manufacturing"},{"docCount":6,"key":"retail"}]},"logoUrl":"https://s3.amazonaws.com/top-local-agencies/profiles/logos/000/030/932/original/tack_logo.png","name":"Tack Media","physicalLocations":[{"city":"Los Angeles","countryCode":"US","id":"0fbfb300-9747-41df-b24a-16845a73cba1","state":"California"}],"primaryLocation":{"city":"Los Angeles","countryCode":"US","id":"0fbfb300-9747-41df-b24a-16845a73cba1","state":"California"},"projectBasedBudget":null,"reviewSummary":{"rating":{"rating":1},"totalCount":13},"services":[{"id":"branding","name":"Branding"},{"id":"digital-marketing","name":"Digital Marketing"},{"id":"full-service-digital","name":"Full Service Digital"},{"id":"seo","name":"SEO"},{"id":"social-media-marketing","name":"Social Media Marketing"},{"id":"web-design","name":"Web Design"},{"id":"web-development","name":"Web Development"}],"slug":"tack-media","tagline":"California-based internet marketing and media firm","technologies":[],"verified":true,"websiteUrl":"https://www.tackmedia.com","yearFounded":2003}},{"node":{"alternateId":3409,"campaign":null,"clientBudget":2,"employeeRangeId":1,"id":"3c117f2d-d4dd-376c-99db-16a28c2d8a70","industries":["Construction","Hospital & Health Care","Individual & Family Services","Industrial Automation","Information Services","Leisure, Travel & Tourism"],"insights":{"projectCost":[{"docCount":13,"key":"total"},{"docCount":2,"key":"Unspecified"},{"docCount":1,"key":"G"},{"docCount":10,"key":"A"}],"projectMonthlyCost":[{"docCount":13,"key":"total"},{"docCount":1,"key":"C"},{"docCount":4,"key":"Unspecified"},{"docCount":3,"key":"F"},{"docCount":5,"key":"A"}],"reviewerCompanySize":[{"docCount":13,"key":"total"},{"docCount":11,"key":"Unspecified"},{"docCount":2,"key":"D"}],"reviewerIndustry":[{"docCount":10,"key":"total"},{"docCount":3,"key":"construction"},{"docCount":1,"key":"finance"},{"docCount":1,"key":"health"},{"docCount":1,"key":"hospitality"},{"docCount":1,"key":"it"},{"docCount":1,"key":"professional"},{"docCount":2,"key":"retail"}]},"logoUrl":"https://s3.amazonaws.com/top-local-agencies/profiles/logos/000/069/153/original/Hometown_Creatives_Logow.png","name":"Hometown Creatives","physicalLocations":[{"city":"Knoxville","countryCode":"US","id":"4c6705ce-a224-4356-a623-c57c88b3994c","state":"Tennessee"}],"primaryLocation":{"city":"Knoxville","countryCode":"US","id":"4c6705ce-a224-4356-a623-c57c88b3994c","state":"Tennessee"},"projectBasedBudget":2,"reviewSummary":{"rating":{"rating":1},"totalCount":13},"services":[{"id":"creative","name":"Creative"},{"id":"digital-marketing","name":"Digital Marketing"},{"id":"ppc","name":"PPC"},{"id":"seo","name":"SEO"},{"id":"social-media-marketing","name":"Social Media Marketing"},{"id":"web-design","name":"Web Design"},{"id":"web-development","name":"Web Development"}],"slug":"hometown-creatives","tagline":"Tennessee-based digital marketing agency","technologies":[],"verified":true,"websiteUrl":"https://hometowncreatives.com","yearFounded":2019}},{"node":{"alternateId":10253,"campaign":null,"clientBudget":3,"employeeRangeId":1,"id":"1e1af919-4619-ea8c-76e4-3512bad383a9","industries":["Information Services"],"insights":{"projectCost":[{"docCount":13,"key":"total"},{"docCount":6,"key":"A"},{"docCount":4,"key":"G"},{"docCount":1,"key":"Unspecified"},{"docCount":2,"key":"B"}],"projectMonthlyCost":[{"docCount":13,"key":"total"},{"docCount":3,"key":"D"},{"docCount":1,"key":"Unspecified"},{"docCount":3,"key":"C"},{"docCount":5,"key":"F"},{"docCount":1,"key":"B"}],"reviewerCompanySize":[{"docCount":13,"key":"total"},{"docCount":4,"key":"D"},{"docCount":9,"key":"Unspecified"}],"reviewerIndustry":[{"docCount":10,"key":"total"},{"docCount":1,"key":"arts"},{"docCount":3,"key":"construction"},{"docCount":1,"key":"it"},{"docCount":1,"key":"legal"},{"docCount":2,"key":"professional"},{"docCount":1,"key":"real_estate"},{"docCount":1,"key":"retail"}]},"logoUrl":"https://s3.amazonaws.com/top-local-agencies/profiles/logos/000/031/611/original/Social_Firm_Logo_Horizontal_Full_Color_Transparent_500px_(1)_(1).png","name":"Social Firm","physicalLocations":[{"city":"Columbus","countryCode":"US","id":"ec85691e-52df-4edc-accb-2ec9ed001323","state":"Ohio"}],"primaryLocation":{"city":"Columbus","countryCode":"US","id":"ec85691e-52df-4edc-accb-2ec9ed001323","state":"Ohio"},"projectBasedBudget":4,"reviewSummary":{"rating":{"rating":1},"totalCount":13},"services":[{"id":"creative","name":"Creative"},{"id":"digital-marketing","name":"Digital Marketing"},{"id":"email-marketing","name":"Email Marketing"},{"id":"graphic-design","name":"Graphic Design"},{"id":"logo-design","name":"Logo Design"},{"id":"ppc","name":"PPC"},{"id":"public-relations-pr","name":"Public Relations (PR)"},{"id":"seo","name":"SEO"},{"id":"social-media-marketing","name":"Social Media Marketing"},{"id":"web-design","name":"Web Design"}],"slug":"social-firm","tagline":"Columbus, Ohio based digital marketing agency","technologies":[],"verified":true,"websiteUrl":"https://socialfirm.com","yearFounded":2010}},{"node":{"alternateId":9406,"campaign":null,"clientBudget":4,"employeeRangeId":2,"id":"9f83d6ab-67ab-324a-b008-fe9f526fe540","industries":["Information Services"],"insights":{"projectCost":[{"docCount":13,"key":"total"},{"docCount":10,"key":"Unspecified"},{"docCount":1,"key":"B"},{"docCount":2,"key":"A"}],"projectMonthlyCost":[{"docCount":13,"key":"total"},{"docCount":10,"key":"Unspecified"},{"docCount":2,"key":"C"},{"docCount":1,"key":"B"}],"reviewerCompanySize":[{"docCount":13,"key":"total"},{"docCount":12,"key":"Unspecified"},{"docCount":1,"key":"D"}],"reviewerIndustry":[{"docCount":5,"key":"total"},{"docCount":2,"key":"finance"},{"docCount":1,"key":"health"},{"docCount":1,"key":"it"},{"docCount":1,"key":"retail"}]},"logoUrl":"https://s3.amazonaws.com/top-local-agencies/profiles/logos/000/055/740/original/JM_02_black.jpg","name":"JoshMeah&Company","physicalLocations":[{"city":"Summit","countryCode":"US","id":"1eea34f8-b094-43f7-abce-35916d4179f0","state":"New Jersey"},{"city":"New York","countryCode":"US","id":"984386c9-9a9c-445a-a516-a7c85aaeac4f","state":"New York"}],"primaryLocation":{"city":"Summit","countryCode":"US","id":"1eea34f8-b094-43f7-abce-35916d4179f0","state":"New Jersey"},"projectBasedBudget":3,"reviewSummary":{"rating":{"rating":1},"totalCount":13},"services":[{"id":"advertising","name":"Advertising"},{"id":"branding","name":"Branding"},{"id":"content-marketing","name":"Content Marketing"},{"id":"creative","name":"Creative"},{"id":"digital-marketing","name":"Digital Marketing"},{"id":"email-marketing","name":"Email Marketing"},{"id":"graphic-design","name":"Graphic Design"},{"id":"mobile-app-development","name":"Mobile App Development"},{"id":"ppc","name":"PPC"},{"id":"seo","name":"SEO"},{"id":"social-media-marketing","name":"Social Media Marketing"},{"id":"video-production","name":"Video Production"},{"id":"web-design","name":"Web Design"},{"id":"web-development","name":"Web Development"}],"slug":"joshmeah-company","tagline":"Digital media and brand development agency","technologies":[],"verified":true,"websiteUrl":"https://www.joshmeah.com","yearFounded":2018}},{"node":{"alternateId":9894,"campaign":null,"clientBudget":2,"employeeRangeId":1,"id":"82f39f0e-6429-4029-6733-c51c239fff25","industries":["Automotive","Consumer Services","Information Services"],"insights":{"projectCost":[{"docCount":13,"key":"total"},{"docCount":3,"key":"G"},{"docCount":6,"key":"Unspecified"},{"docCount":4,"key":"A"}],"projectMonthlyCost":[{"docCount":13,"key":"total"},{"docCount":3,"key":"F"},{"docCount":6,"key":"C"},{"docCount":1,"key":"B"},{"docCount":1,"key":"Unspecified"},{"docCount":2,"key":"D"}],"reviewerCompanySize":[{"docCount":13,"key":"total"},{"docCount":6,"key":"Unspecified"},{"docCount":7,"key":"D"}],"reviewerIndustry":[{"docCount":10,"key":"total"},{"docCount":2,"key":"health"},{"docCount":1,"key":"manufacturing"},{"docCount":5,"key":"retail"},{"docCount":2,"key":"transportation"}]},"logoUrl":"https://s3.amazonaws.com/top-local-agencies/profiles/logos/000/062/089/original/CRP_Logo_Color.png","name":"CRP Marketing","physicalLocations":[{"city":"Chico","countryCode":"US","id":"ee2fdb94-1fe1-47a3-acb8-5b967aed4482","state":"California"}],"primaryLocation":{"city":"Chico","countryCode":"US","id":"ee2fdb94-1fe1-47a3-acb8-5b967aed4482","state":"California"},"projectBasedBudget":2,"reviewSummary":{"rating":{"rating":1},"totalCount":13},"services":[{"id":"advertising","name":"Advertising"},{"id":"content-marketing","name":"Content Marketing"},{"id":"digital-marketing","name":"Digital Marketing"},{"id":"email-marketing","name":"Email Marketing"},{"id":"seo","name":"SEO"},{"id":"social-media-marketing","name":"Social Media Marketing"},{"id":"video-production","name":"Video Production"},{"id":"web-design","name":"Web Design"}],"slug":"crp-marketing","tagline":"California-based digital marketing and advertising company","technologies":[],"verified":true,"websiteUrl":"https://www.crpmarketing.com","yearFounded":2018}},{"node":{"alternateId":2598,"campaign":null,"clientBudget":5,"employeeRangeId":2,"id":"68a8583b-5f26-670e-bc3c-ba0705e4cc4c","industries":["Hospitality","Medical Practice"],"insights":{"projectCost":[{"docCount":13,"key":"total"},{"docCount":6,"key":"G"},{"docCount":1,"key":"Unspecified"},{"docCount":4,"key":"A"},{"docCount":2,"key":"B"}],"projectMonthlyCost":[{"docCount":13,"key":"total"},{"docCount":5,"key":"F"},{"docCount":2,"key":"D"},{"docCount":2,"key":"C"},{"docCount":1,"key":"B"},{"docCount":3,"key":"Unspecified"}],"reviewerCompanySize":[{"docCount":13,"key":"total"},{"docCount":4,"key":"Unspecified"},{"docCount":9,"key":"D"}],"reviewerIndustry":[{"docCount":11,"key":"total"},{"docCount":11,"key":"health"}]},"logoUrl":"https://s3.amazonaws.com/top-local-agencies/profiles/logos/000/213/056/original/TM_Primary_Hor_Full_Color.png","name":"TrackableMed","physicalLocations":[{"city":"Covington","countryCode":"US","id":"ac7678d3-dec2-4e1b-976c-01626c10469e","state":"Louisiana"}],"primaryLocation":{"city":"Covington","countryCode":"US","id":"ac7678d3-dec2-4e1b-976c-01626c10469e","state":"Louisiana"},"projectBasedBudget":5,"reviewSummary":{"rating":{"rating":1},"totalCount":13},"services":[{"id":"advertising","name":"Advertising"},{"id":"digital-marketing","name":"Digital Marketing"},{"id":"full-service-digital","name":"Full Service Digital"},{"id":"ppc","name":"PPC"},{"id":"seo","name":"SEO"},{"id":"web-design","name":"Web Design"}],"slug":"trackablemed","tagline":"Advertising, digital marketing & website development agency","technologies":[],"verified":true,"websiteUrl":"https://www.trackablemed.com","yearFounded":2011}},{"node":{"alternateId":4004,"campaign":null,"clientBudget":4,"employeeRangeId":1,"id":"e560f3d7-6a57-042f-5bf3-6f2c73e501ad","industries":["Information Services","Medical Practice"],"insights":{"projectCost":[{"docCount":13,"key":"total"},{"docCount":8,"key":"A"},{"docCount":3,"key":"G"},{"docCount":2,"key":"Unspecified"}],"projectMonthlyCost":[{"docCount":13,"key":"total"},{"docCount":2,"key":"B"},{"docCount":1,"key":"A"},{"docCount":2,"key":"Unspecified"},{"docCount":8,"key":"F"}],"reviewerCompanySize":[{"docCount":13,"key":"total"},{"docCount":11,"key":"Unspecified"},{"docCount":2,"key":"D"}],"reviewerIndustry":[{"docCount":11,"key":"total"},{"docCount":1,"key":"education"},{"docCount":2,"key":"finance"},{"docCount":1,"key":"health"},{"docCount":1,"key":"hospitality"},{"docCount":1,"key":"professional"},{"docCount":2,"key":"public"},{"docCount":3,"key":"retail"}]},"logoUrl":"https://s3.amazonaws.com/top-local-agencies/profiles/logos/000/007/109/original/LiquisLogo_Mark_Blue.png","name":"Liquis Digital","physicalLocations":[{"city":"Peoria","countryCode":"US","id":"ed41a82c-337d-4f22-b3f1-6aa860e62e23","state":"Arizona"}],"primaryLocation":{"city":"Peoria","countryCode":"US","id":"ed41a82c-337d-4f22-b3f1-6aa860e62e23","state":"Arizona"},"projectBasedBudget":4,"reviewSummary":{"rating":{"rating":1},"totalCount":13},"services":[{"id":"digital-marketing","name":"Digital Marketing"},{"id":"seo","name":"SEO"},{"id":"social-media-marketing","name":"Social Media Marketing"},{"id":"web-design","name":"Web Design"}],"slug":"liquis-digital","tagline":"Web design and digital marketing agency","technologies":[],"verified":true,"websiteUrl":"https://liquisdigital.com","yearFounded":2008}},{"node":{"alternateId":11654,"campaign":null,"clientBudget":3,"employeeRangeId":2,"id":"adca262a-3d63-da47-8231-5374dd78251d","industries":["Consumer Services","Education Management","Entertainment","Industrial Automation","Information Services","Law Practice"],"insights":{"projectCost":[{"docCount":13,"key":"total"},{"docCount":3,"key":"A"},{"docCount":3,"key":"Unspecified"},{"docCount":2,"key":"G"},{"docCount":5,"key":"B"}],"projectMonthlyCost":[{"docCount":13,"key":"total"},{"docCount":1,"key":"E"},{"docCount":5,"key":"C"},{"docCount":4,"key":"F"},{"docCount":1,"key":"A"},{"docCount":2,"key":"Unspecified"}],"reviewerCompanySize":[{"docCount":13,"key":"total"},{"docCount":3,"key":"D"},{"docCount":10,"key":"Unspecified"}],"reviewerIndustry":[{"docCount":9,"key":"total"},{"docCount":2,"key":"education"},{"docCount":4,"key":"health"},{"docCount":1,"key":"hospitality"},{"docCount":1,"key":"manufacturing"},{"docCount":1,"key":"retail"}]},"logoUrl":"https://s3.amazonaws.com/top-local-agencies/profiles/logos/000/017/285/original/data","name":"OptFirst Internet Marketing","physicalLocations":[{"city":"North Miami","countryCode":"US","id":"77dad23c-8aa1-418d-b4b2-56cac6630277","state":"Florida"}],"primaryLocation":{"city":"North Miami","countryCode":"US","id":"77dad23c-8aa1-418d-b4b2-56cac6630277","state":"Florida"},"projectBasedBudget":4,"reviewSummary":{"rating":{"rating":1},"totalCount":13},"services":[{"id":"advertising","name":"Advertising"},{"id":"branding","name":"Branding"},{"id":"content-marketing","name":"Content Marketing"},{"id":"digital-marketing","name":"Digital Marketing"},{"id":"email-marketing","name":"Email Marketing"},{"id":"ppc","name":"PPC"},{"id":"seo","name":"SEO"},{"id":"user-experience-design","name":"User Experience Design"},{"id":"web-design","name":"Web Design"},{"id":"web-development","name":"Web Development"}],"slug":"optfirst-internet-marketing","tagline":"Miami-based SEO and website development service provider","technologies":[],"verified":true,"websiteUrl":"https://www.optfirst.com","yearFounded":2001}},{"node":{"alternateId":5260,"campaign":null,"clientBudget":5,"employeeRangeId":2,"id":"5949e994-78fb-64b8-1240-e5bd447a9093","industries":["Consumer Services","Entertainment","Health, Wellness and Fitness","Industrial Automation","Information Services","Retail"],"insights":{"projectCost":[{"docCount":13,"key":"total"},{"docCount":10,"key":"Unspecified"},{"docCount":2,"key":"B"},{"docCount":1,"key":"A"}],"projectMonthlyCost":[{"docCount":13,"key":"total"},{"docCount":1,"key":"D"},{"docCount":1,"key":"E"},{"docCount":10,"key":"Unspecified"},{"docCount":1,"key":"F"}],"reviewerCompanySize":[{"docCount":13,"key":"total"},{"docCount":13,"key":"Unspecified"}],"reviewerIndustry":[{"docCount":4,"key":"total"},{"docCount":1,"key":"health"},{"docCount":3,"key":"retail"}]},"logoUrl":"https://s3.amazonaws.com/top-local-agencies/profiles/logos/000/026/253/original/Eventige-Media-Group-Icon-Square.png","name":"Eventige Media Group","physicalLocations":[{"city":"New York City","countryCode":"US","id":"50cf890d-f956-4d4d-a251-956aedd3e0ee","state":"New York"}],"primaryLocation":{"city":"New York City","countryCode":"US","id":"50cf890d-f956-4d4d-a251-956aedd3e0ee","state":"New York"},"projectBasedBudget":4,"reviewSummary":{"rating":{"rating":1},"totalCount":13},"services":[{"id":"advertising","name":"Advertising"},{"id":"branding","name":"Branding"},{"id":"digital-marketing","name":"Digital Marketing"},{"id":"full-service-digital","name":"Full Service Digital"},{"id":"seo","name":"SEO"},{"id":"social-media-marketing","name":"Social Media Marketing"},{"id":"user-experience-design","name":"User Experience Design"},{"id":"web-design","name":"Web Design"},{"id":"web-development","name":"Web Development"}],"slug":"eventige-media-group","tagline":"Full-service digital marketing and branding agency","technologies":[],"verified":true,"websiteUrl":"https://www.eventige.com","yearFounded":2008}},{"node":{"alternateId":8691,"campaign":null,"clientBudget":1,"employeeRangeId":2,"id":"532dad7f-3d46-729f-9871-af736c2ae3a0","industries":["Consumer Services","Industrial Automation","Information Services","Non-Profit Organization Management","Restaurants","Think Tanks"],"insights":{"projectCost":[{"docCount":13,"key":"total"},{"docCount":9,"key":"Unspecified"},{"docCount":1,"key":"B"},{"docCount":1,"key":"A"},{"docCount":2,"key":"G"}],"projectMonthlyCost":[{"docCount":13,"key":"total"},{"docCount":9,"key":"Unspecified"},{"docCount":3,"key":"F"},{"docCount":1,"key":"C"}],"reviewerCompanySize":[{"docCount":13,"key":"total"},{"docCount":2,"key":"D"},{"docCount":11,"key":"Unspecified"}],"reviewerIndustry":[{"docCount":3,"key":"total"},{"docCount":1,"key":"construction"},{"docCount":1,"key":"manufacturing"},{"docCount":1,"key":"public"}]},"logoUrl":"https://s3.amazonaws.com/top-local-agencies/profiles/logos/000/002/082/original/baseline-black.jpg","name":"Baseline Creative","physicalLocations":[{"city":"Wichita","countryCode":"US","id":"e2750e2e-9f41-4672-9315-ea68ac914ed7","state":"Kansas"}],"primaryLocation":{"city":"Wichita","countryCode":"US","id":"e2750e2e-9f41-4672-9315-ea68ac914ed7","state":"Kansas"},"projectBasedBudget":3,"reviewSummary":{"rating":{"rating":1},"totalCount":13},"services":[{"id":"branding","name":"Branding"},{"id":"content-marketing","name":"Content Marketing"},{"id":"creative","name":"Creative"},{"id":"digital-marketing","name":"Digital Marketing"},{"id":"email-marketing","name":"Email Marketing"},{"id":"graphic-design","name":"Graphic Design"},{"id":"logo-design","name":"Logo Design"},{"id":"ppc","name":"PPC"},{"id":"public-relations-pr","name":"Public Relations (PR)"},{"id":"seo","name":"SEO"},{"id":"social-media-marketing","name":"Social Media Marketing"},{"id":"web-design","name":"Web Design"},{"id":"web-development","name":"Web Development"}],"slug":"baseline-creative","tagline":"Full-service web design and digital marketing agency","technologies":[],"verified":true,"websiteUrl":"https://baselinecreative.com","yearFounded":2005}},{"node":{"alternateId":8183,"campaign":null,"clientBudget":5,"employeeRangeId":2,"id":"46408d31-1834-b5cb-7e62-318221531b07","industries":["Law Practice"],"insights":{"projectCost":[{"docCount":13,"key":"total"},{"docCount":4,"key":"A"},{"docCount":5,"key":"G"},{"docCount":2,"key":"B"},{"docCount":2,"key":"Unspecified"}],"projectMonthlyCost":[{"docCount":13,"key":"total"},{"docCount":2,"key":"Unspecified"},{"docCount":7,"key":"F"},{"docCount":3,"key":"E"},{"docCount":1,"key":"C"}],"reviewerCompanySize":[{"docCount":13,"key":"total"},{"docCount":3,"key":"D"},{"docCount":10,"key":"Unspecified"}],"reviewerIndustry":[{"docCount":0,"key":"total"}]},"logoUrl":"https://s3.amazonaws.com/top-local-agencies/profiles/logos/000/067/795/original/LawRank-ranktracker.png","name":"LawRank","physicalLocations":[{"city":"San Diego","countryCode":"US","id":"b252b1b7-da23-47ea-9ca7-0d72510a82ed","state":"California"}],"primaryLocation":{"city":"San Diego","countryCode":"US","id":"b252b1b7-da23-47ea-9ca7-0d72510a82ed","state":"California"},"projectBasedBudget":4,"reviewSummary":{"rating":{"rating":1},"totalCount":13},"services":[{"id":"advertising","name":"Advertising"},{"id":"digital-marketing","name":"Digital Marketing"},{"id":"ppc","name":"PPC"},{"id":"seo","name":"SEO"},{"id":"social-media-marketing","name":"Social Media Marketing"},{"id":"web-design","name":"Web Design"},{"id":"web-development","name":"Web Development"}],"slug":"lawrank","tagline":"SEO and advertising agency for law firms","technologies":[],"verified":true,"websiteUrl":"https://lawrank.com","yearFounded":2013}},{"node":{"alternateId":9822,"campaign":null,"clientBudget":5,"employeeRangeId":2,"id":"009564b9-8922-d877-431e-122c028e3b8a","industries":["Food & Beverages","Hospitality","Industrial Automation","Information Services","Retail"],"insights":{"projectCost":[{"docCount":13,"key":"total"},{"docCount":2,"key":"A"},{"docCount":5,"key":"Unspecified"},{"docCount":6,"key":"B"}],"projectMonthlyCost":[{"docCount":13,"key":"total"},{"docCount":2,"key":"F"},{"docCount":5,"key":"D"},{"docCount":3,"key":"E"},{"docCount":1,"key":"C"},{"docCount":2,"key":"Unspecified"}],"reviewerCompanySize":[{"docCount":13,"key":"total"},{"docCount":13,"key":"Unspecified"}],"reviewerIndustry":[{"docCount":10,"key":"total"},{"docCount":1,"key":"arts"},{"docCount":2,"key":"hospitality"},{"docCount":2,"key":"professional"},{"docCount":5,"key":"retail"}]},"logoUrl":"https://s3.amazonaws.com/top-local-agencies/profiles/logos/000/060/740/original/logo.png","name":"1o8 ","physicalLocations":[{"city":"Chicago","countryCode":"US","id":"28dcf9dc-ef3a-4b03-b05e-fc810a44efd8","state":"Illinois"}],"primaryLocation":{"city":"Chicago","countryCode":"US","id":"28dcf9dc-ef3a-4b03-b05e-fc810a44efd8","state":"Illinois"},"projectBasedBudget":5,"reviewSummary":{"rating":{"rating":1},"totalCount":13},"services":[{"id":"advertising","name":"Advertising"},{"id":"branding","name":"Branding"},{"id":"digital-marketing","name":"Digital Marketing"},{"id":"full-service-digital","name":"Full Service Digital"},{"id":"seo","name":"SEO"},{"id":"social-media-marketing","name":"Social Media Marketing"},{"id":"video-production","name":"Video Production"}],"slug":"1o8","tagline":"Digital marketing, advertising, and video production agency","technologies":[],"verified":true,"websiteUrl":"https://1o8.agency","yearFounded":2018}},{"node":{"alternateId":4301,"campaign":null,"clientBudget":2,"employeeRangeId":2,"id":"8ae1dc93-efe9-beda-df00-9513f6bade7c","industries":["Consumer Services","Hospitality","Individual & Family Services","Information Services","Law Practice","Medical Practice"],"insights":{"projectCost":[{"docCount":13,"key":"total"},{"docCount":4,"key":"Unspecified"},{"docCount":3,"key":"B"},{"docCount":6,"key":"A"}],"projectMonthlyCost":[{"docCount":13,"key":"total"},{"docCount":4,"key":"C"},{"docCount":3,"key":"D"},{"docCount":2,"key":"B"},{"docCount":4,"key":"Unspecified"}],"reviewerCompanySize":[{"docCount":13,"key":"total"},{"docCount":1,"key":"D"},{"docCount":12,"key":"Unspecified"}],"reviewerIndustry":[{"docCount":6,"key":"total"},{"docCount":2,"key":"finance"},{"docCount":2,"key":"health"},{"docCount":1,"key":"manufacturing"},{"docCount":1,"key":"transportation"}]},"logoUrl":"https://s3.amazonaws.com/top-local-agencies/profiles/logos/000/009/365/original/flat-logo-200px-purple_bg_white_icon.png","name":"Search Control","physicalLocations":[{"city":"Scottsdale","countryCode":"US","id":"a8c2426c-d532-4d45-a96b-ab615c69eafd","state":"Arizona"}],"primaryLocation":{"city":"Scottsdale","countryCode":"US","id":"a8c2426c-d532-4d45-a96b-ab615c69eafd","state":"Arizona"},"projectBasedBudget":2,"reviewSummary":{"rating":{"rating":1},"totalCount":13},"services":[{"id":"branding","name":"Branding"},{"id":"content-marketing","name":"Content Marketing"},{"id":"digital-marketing","name":"Digital Marketing"},{"id":"email-marketing","name":"Email Marketing"},{"id":"full-service-digital","name":"Full Service Digital"},{"id":"ppc","name":"PPC"},{"id":"seo","name":"SEO"},{"id":"social-media-marketing","name":"Social Media Marketing"},{"id":"web-design","name":"Web Design"},{"id":"web-development","name":"Web Development"}],"slug":"search-control","tagline":"Full-service digital marketing agency located in Arizona","technologies":[],"verified":true,"websiteUrl":"https://www.searchcontrol.com","yearFounded":2009}},{"node":{"alternateId":8214,"campaign":null,"clientBudget":5,"employeeRangeId":1,"id":"75d1c291-504b-dbf1-a4f3-29adc26351ee","industries":["Consumer Services","Entertainment","Information Services","Leisure, Travel & Tourism","Sports","Think Tanks"],"insights":{"projectCost":[{"docCount":13,"key":"total"},{"docCount":2,"key":"Unspecified"},{"docCount":11,"key":"A"}],"projectMonthlyCost":[{"docCount":13,"key":"total"},{"docCount":1,"key":"E"},{"docCount":8,"key":"Unspecified"},{"docCount":3,"key":"F"},{"docCount":1,"key":"A"}],"reviewerCompanySize":[{"docCount":13,"key":"total"},{"docCount":10,"key":"Unspecified"},{"docCount":3,"key":"D"}],"reviewerIndustry":[{"docCount":12,"key":"total"},{"docCount":1,"key":"education"},{"docCount":1,"key":"health"},{"docCount":2,"key":"hospitality"},{"docCount":2,"key":"professional"},{"docCount":6,"key":"retail"}]},"logoUrl":"https://s3.amazonaws.com/top-local-agencies/profiles/logos/000/095/533/original/Logo_Linkedin_II.jpg","name":"STMNT Studios","physicalLocations":[{"city":"San Francisco","countryCode":"US","id":"1994622d-5594-4fc1-a444-3a52644d937b","state":"California"}],"primaryLocation":{"city":"San Francisco","countryCode":"US","id":"1994622d-5594-4fc1-a444-3a52644d937b","state":"California"},"projectBasedBudget":4,"reviewSummary":{"rating":{"rating":1},"totalCount":13},"services":[{"id":"digital-marketing","name":"Digital Marketing"},{"id":"video-production","name":"Video Production"}],"slug":"stmnt-studios","tagline":"Full-service video production and digital marketing agency","technologies":[],"verified":true,"websiteUrl":"https://www.stmntstudios.com","yearFounded":2018}},{"node":{"alternateId":8566,"campaign":null,"clientBudget":2,"employeeRangeId":2,"id":"201ffea8-5b87-1a05-0e5a-c8934fe88f02","industries":["Construction","Hospitality","Individual & Family Services"],"insights":{"projectCost":[{"docCount":13,"key":"total"},{"docCount":1,"key":"G"},{"docCount":1,"key":"B"},{"docCount":4,"key":"Unspecified"},{"docCount":7,"key":"A"}],"projectMonthlyCost":[{"docCount":13,"key":"total"},{"docCount":1,"key":"E"},{"docCount":1,"key":"D"},{"docCount":4,"key":"Unspecified"},{"docCount":1,"key":"C"},{"docCount":4,"key":"F"},{"docCount":2,"key":"A"}],"reviewerCompanySize":[{"docCount":13,"key":"total"},{"docCount":1,"key":"D"},{"docCount":12,"key":"Unspecified"}],"reviewerIndustry":[{"docCount":9,"key":"total"},{"docCount":2,"key":"arts"},{"docCount":1,"key":"construction"},{"docCount":1,"key":"education"},{"docCount":1,"key":"it"},{"docCount":2,"key":"public"},{"docCount":2,"key":"retail"}]},"logoUrl":"https://s3.amazonaws.com/top-local-agencies/profiles/logos/000/002/687/original/Elevated_Ecommerce_-_400.jpg","name":"Elevated E-Commerce & Web Design","physicalLocations":[{"city":"Omaha","countryCode":"US","id":"2264753c-02fb-4018-a3da-bbf53f306551","state":"Nebraska"}],"primaryLocation":{"city":"Omaha","countryCode":"US","id":"2264753c-02fb-4018-a3da-bbf53f306551","state":"Nebraska"},"projectBasedBudget":3,"reviewSummary":{"rating":{"rating":1},"totalCount":13},"services":[{"id":"branding","name":"Branding"},{"id":"digital-marketing","name":"Digital Marketing"},{"id":"email-marketing","name":"Email Marketing"},{"id":"full-service-digital","name":"Full Service Digital"},{"id":"ppc","name":"PPC"},{"id":"seo","name":"SEO"},{"id":"social-media-marketing","name":"Social Media Marketing"},{"id":"web-design","name":"Web Design"},{"id":"web-development","name":"Web Development"}],"slug":"elevated-e-commerce-web-design","tagline":"Full-service digital marketing and web design company","technologies":[],"verified":true,"websiteUrl":"https://elevatedseo.com","yearFounded":2010}},{"node":{"alternateId":9137,"campaign":null,"clientBudget":5,"employeeRangeId":3,"id":"d9a39c50-aafc-42db-90a7-129abb889e16","industries":["Accounting","Education Management","Hospitality","Information Services","Non-Profit Organization Management"],"insights":{"projectCost":[{"docCount":13,"key":"total"},{"docCount":6,"key":"B"},{"docCount":7,"key":"Unspecified"}],"projectMonthlyCost":[{"docCount":13,"key":"total"},{"docCount":1,"key":"F"},{"docCount":8,"key":"Unspecified"},{"docCount":4,"key":"E"}],"reviewerCompanySize":[{"docCount":13,"key":"total"},{"docCount":13,"key":"Unspecified"}],"reviewerIndustry":[{"docCount":7,"key":"total"},{"docCount":2,"key":"finance"},{"docCount":4,"key":"it"},{"docCount":1,"key":"real_estate"}]},"logoUrl":"https://s3.amazonaws.com/top-local-agencies/profiles/logos/000/000/723/original/Facebook_Profile_Image_2.png","name":"Three Five Two","physicalLocations":[{"city":"Atlanta","countryCode":"US","id":"58e3351f-7ac1-465d-bb8c-013226ad26df","state":"Georgia"},{"city":"Tampa","countryCode":"US","id":"241c2c79-6135-4bd8-8d01-b5a532e37c39","state":"Florida"},{"city":"Gainesville","countryCode":"US","id":"ce50ba8a-ff46-44df-a265-38d16a8efe6b","state":"Florida"}],"primaryLocation":{"city":"Atlanta","countryCode":"US","id":"58e3351f-7ac1-465d-bb8c-013226ad26df","state":"Georgia"},"projectBasedBudget":null,"reviewSummary":{"rating":{"rating":1},"totalCount":13},"services":[{"id":"advertising","name":"Advertising"},{"id":"branding","name":"Branding"},{"id":"design","name":"Design"},{"id":"digital-marketing","name":"Digital Marketing"},{"id":"full-service-digital","name":"Full Service Digital"},{"id":"user-experience-design","name":"User Experience Design"},{"id":"web-design","name":"Web Design"},{"id":"web-development","name":"Web Development"}],"slug":"three-five-two","tagline":"Product strategy and development company in Florida","technologies":[],"verified":true,"websiteUrl":"https://www.threefivetwo.com","yearFounded":2023}},{"node":{"alternateId":16037,"campaign":null,"clientBudget":3,"employeeRangeId":2,"id":"de05693f-7959-2c82-bb4f-1d848679f849","industries":["Individual & Family Services","Information Services","Law Practice","Non-Profit Organization Management","Think Tanks"],"insights":{"projectCost":[{"docCount":13,"key":"total"},{"docCount":7,"key":"Unspecified"},{"docCount":3,"key":"A"},{"docCount":2,"key":"G"},{"docCount":1,"key":"B"}],"projectMonthlyCost":[{"docCount":13,"key":"total"},{"docCount":2,"key":"F"},{"docCount":1,"key":"C"},{"docCount":9,"key":"Unspecified"},{"docCount":1,"key":"B"}],"reviewerCompanySize":[{"docCount":13,"key":"total"},{"docCount":13,"key":"Unspecified"}],"reviewerIndustry":[{"docCount":5,"key":"total"},{"docCount":1,"key":"hospitality"},{"docCount":1,"key":"real_estate"},{"docCount":3,"key":"retail"}]},"logoUrl":"https://s3.amazonaws.com/top-local-agencies/profiles/logos/000/053/993/original/smblk.png","name":"South Made Marketing","physicalLocations":[{"city":"Knoxville","countryCode":"US","id":"4c6705ce-a224-4356-a623-c57c88b3994c","state":"Tennessee"}],"primaryLocation":{"city":"Knoxville","countryCode":"US","id":"4c6705ce-a224-4356-a623-c57c88b3994c","state":"Tennessee"},"projectBasedBudget":null,"reviewSummary":{"rating":{"rating":1},"totalCount":13},"services":[{"id":"branding","name":"Branding"},{"id":"digital-marketing","name":"Digital Marketing"},{"id":"email-marketing","name":"Email Marketing"},{"id":"graphic-design","name":"Graphic Design"},{"id":"ppc","name":"PPC"},{"id":"seo","name":"SEO"},{"id":"social-media-marketing","name":"Social Media Marketing"},{"id":"video-production","name":"Video Production"},{"id":"web-design","name":"Web Design"},{"id":"web-development","name":"Web Development"}],"slug":"south-made-marketing","tagline":"Digital marketing, branding and website design company","technologies":[],"verified":true,"websiteUrl":"https://southmade.com","yearFounded":2007}},{"node":{"alternateId":16755,"campaign":null,"clientBudget":4,"employeeRangeId":2,"id":"7a047946-486e-485a-407f-4e62dbf358a9","industries":["Consumer Services","Education Management","Information Services","Non-Profit Organization Management","Retail","Sports"],"insights":{"projectCost":[{"docCount":13,"key":"total"},{"docCount":3,"key":"A"},{"docCount":1,"key":"G"},{"docCount":9,"key":"Unspecified"}],"projectMonthlyCost":[{"docCount":13,"key":"total"},{"docCount":1,"key":"F"},{"docCount":2,"key":"B"},{"docCount":1,"key":"D"},{"docCount":9,"key":"Unspecified"}],"reviewerCompanySize":[{"docCount":13,"key":"total"},{"docCount":13,"key":"Unspecified"}],"reviewerIndustry":[{"docCount":4,"key":"total"},{"docCount":1,"key":"health"},{"docCount":1,"key":"hospitality"},{"docCount":1,"key":"it"},{"docCount":1,"key":"professional"}]},"logoUrl":"https://s3.amazonaws.com/top-local-agencies/profiles/logos/000/055/824/original/SeedXBlack.png","name":"SeedX Inc","physicalLocations":[{"city":"Los Angeles","countryCode":"US","id":"0fbfb300-9747-41df-b24a-16845a73cba1","state":"California"}],"primaryLocation":{"city":"Los Angeles","countryCode":"US","id":"0fbfb300-9747-41df-b24a-16845a73cba1","state":"California"},"projectBasedBudget":null,"reviewSummary":{"rating":{"rating":1},"totalCount":13},"services":[{"id":"advertising","name":"Advertising"},{"id":"branding","name":"Branding"},{"id":"data-analytics","name":"Data Analytics"},{"id":"digital-marketing","name":"Digital Marketing"},{"id":"full-service-digital","name":"Full Service Digital"},{"id":"seo","name":"SEO"},{"id":"social-media-marketing","name":"Social Media Marketing"},{"id":"video-production","name":"Video Production"},{"id":"web-development","name":"Web Development"}],"slug":"seedx-inc","tagline":"Texas-based omnichannel marketing and strategy firm","technologies":[],"verified":true,"websiteUrl":"https://seedx.us","yearFounded":2016}},{"node":{"alternateId":43151,"campaign":null,"clientBudget":2,"employeeRangeId":3,"id":"330374c2-246c-424a-b1f1-473d5e9e2be1","industries":["Accounting","Automotive","Consumer Services","Education Management","Food & Beverages","Government Administration","Hospital & Health Care","Hospitality","Industrial Automation","Information Services","Information Technology and Services","Leisure, Travel & Tourism","Medical Practice","Non-Profit Organization Management","Real Estate","Retail","Think Tanks"],"insights":{"projectCost":[{"docCount":13,"key":"total"},{"docCount":2,"key":"B"},{"docCount":1,"key":"Unspecified"},{"docCount":1,"key":"G"},{"docCount":9,"key":"A"}],"projectMonthlyCost":[{"docCount":13,"key":"total"},{"docCount":3,"key":"B"},{"docCount":1,"key":"F"},{"docCount":1,"key":"D"},{"docCount":1,"key":"Unspecified"},{"docCount":7,"key":"C"}],"reviewerCompanySize":[{"docCount":13,"key":"total"},{"docCount":12,"key":"Unspecified"},{"docCount":1,"key":"D"}],"reviewerIndustry":[{"docCount":11,"key":"total"},{"docCount":1,"key":"construction"},{"docCount":2,"key":"education"},{"docCount":1,"key":"health"},{"docCount":1,"key":"hospitality"},{"docCount":1,"key":"public"},{"docCount":5,"key":"retail"}]},"logoUrl":"https://s3.amazonaws.com/top-local-agencies/profiles/logos/000/278/477/original/logo_ED.png","name":"EvenDigit","physicalLocations":[],"primaryLocation":{"city":null,"countryCode":"AU","id":"19218dbb-c3e8-4845-b2d1-c46e08287e78","state":null},"projectBasedBudget":2,"reviewSummary":{"rating":{"rating":0.98},"totalCount":13},"services":[{"id":"advertising","name":"Advertising"},{"id":"branding","name":"Branding"},{"id":"content-marketing","name":"Content Marketing"},{"id":"creative","name":"Creative"},{"id":"digital-marketing","name":"Digital Marketing"},{"id":"email-marketing","name":"Email Marketing"},{"id":"graphic-design","name":"Graphic Design"},{"id":"lead-generation","name":"Lead Generation"},{"id":"logo-design","name":"Logo Design"},{"id":"ppc","name":"PPC"},{"id":"public-relations-pr","name":"Public Relations (PR)"},{"id":"seo","name":"SEO"},{"id":"social-media-marketing","name":"Social Media Marketing"},{"id":"user-experience-design","name":"User Experience Design"},{"id":"video-production","name":"Video Production"},{"id":"web-design","name":"Web Design"},{"id":"web-development","name":"Web Development"}],"slug":"evendigit","tagline":"Digital marketing and content writing agency in India","technologies":[],"verified":true,"websiteUrl":"https://www.evendigit.com","yearFounded":2009}},{"node":{"alternateId":6262,"campaign":null,"clientBudget":2,"employeeRangeId":4,"id":"e799135b-7be8-7978-92db-3a9fd9840f3a","industries":["Automotive","Consumer Services","Government Administration","Hospitality","Information Services","Retail"],"insights":{"projectCost":[{"docCount":13,"key":"total"},{"docCount":9,"key":"A"},{"docCount":3,"key":"G"},{"docCount":1,"key":"Unspecified"}],"projectMonthlyCost":[{"docCount":13,"key":"total"},{"docCount":3,"key":"B"},{"docCount":1,"key":"D"},{"docCount":5,"key":"A"},{"docCount":3,"key":"F"},{"docCount":1,"key":"Unspecified"}],"reviewerCompanySize":[{"docCount":13,"key":"total"},{"docCount":8,"key":"D"},{"docCount":5,"key":"Unspecified"}],"reviewerIndustry":[{"docCount":12,"key":"total"},{"docCount":1,"key":"education"},{"docCount":1,"key":"it"},{"docCount":8,"key":"retail"},{"docCount":2,"key":"transportation"}]},"logoUrl":"https://s3.amazonaws.com/top-local-agencies/profiles/logos/000/036/735/original/Elsner_logo.png","name":"Elsner Technologies","physicalLocations":[{"city":"Lakeland","countryCode":"US","id":"523a4448-2b29-4c3a-bb3e-ce21d87d3dc4","state":"Florida"},{"city":"Roswell","countryCode":"US","id":"fe32c7ae-5ca7-4d1c-af88-192ea4610003","state":"Georgia"},{"city":"Winnipeg","countryCode":"CA","id":"0c7bd821-dc57-4293-b89b-3ce228e1174b","state":"Manitoba"}],"primaryLocation":{"city":"Lakeland","countryCode":"US","id":"523a4448-2b29-4c3a-bb3e-ce21d87d3dc4","state":"Florida"},"projectBasedBudget":2,"reviewSummary":{"rating":{"rating":0.98},"totalCount":13},"services":[{"id":"advertising","name":"Advertising"},{"id":"branding","name":"Branding"},{"id":"content-marketing","name":"Content Marketing"},{"id":"custom-software-development","name":"Custom Software Development"},{"id":"digital-marketing","name":"Digital Marketing"},{"id":"mobile-app-development","name":"Mobile App Development"},{"id":"ppc","name":"PPC"},{"id":"seo","name":"SEO"},{"id":"social-media-marketing","name":"Social Media Marketing"},{"id":"user-experience-design","name":"User Experience Design"},{"id":"web-design","name":"Web Design"},{"id":"web-development","name":"Web Development"}],"slug":"elsner-technologies","tagline":"E-commerce development and digital marketing agency","technologies":[],"verified":true,"websiteUrl":"https://www.elsner.com","yearFounded":2006}},{"node":{"alternateId":9940,"campaign":null,"clientBudget":4,"employeeRangeId":2,"id":"10078145-8a01-3fb1-bee7-cf074b2e5a00","industries":["Food & Beverages","Health, Wellness and Fitness","Individual & Family Services","Information Services","Restaurants"],"insights":{"projectCost":[{"docCount":13,"key":"total"},{"docCount":4,"key":"Unspecified"},{"docCount":7,"key":"A"},{"docCount":2,"key":"G"}],"projectMonthlyCost":[{"docCount":13,"key":"total"},{"docCount":3,"key":"Unspecified"},{"docCount":1,"key":"A"},{"docCount":5,"key":"F"},{"docCount":2,"key":"D"},{"docCount":2,"key":"C"}],"reviewerCompanySize":[{"docCount":13,"key":"total"},{"docCount":10,"key":"Unspecified"},{"docCount":1,"key":"F"},{"docCount":2,"key":"D"}],"reviewerIndustry":[{"docCount":10,"key":"total"},{"docCount":2,"key":"it"},{"docCount":3,"key":"manufacturing"},{"docCount":2,"key":"professional"},{"docCount":1,"key":"public"},{"docCount":2,"key":"retail"}]},"logoUrl":"https://s3.amazonaws.com/top-local-agencies/profiles/logos/000/009/058/original/k6digital-logodesign-transparent-sm.png","name":"K6 Digital Marketing","physicalLocations":[{"city":"Medina","countryCode":"US","id":"f3e7b326-cf13-45e6-8fc4-883688ef1b2c","state":"Ohio"}],"primaryLocation":{"city":"Medina","countryCode":"US","id":"f3e7b326-cf13-45e6-8fc4-883688ef1b2c","state":"Ohio"},"projectBasedBudget":3,"reviewSummary":{"rating":{"rating":0.98},"totalCount":13},"services":[{"id":"digital-marketing","name":"Digital Marketing"},{"id":"seo","name":"SEO"},{"id":"social-media-marketing","name":"Social Media Marketing"},{"id":"web-design","name":"Web Design"}],"slug":"k6-digital-marketing","tagline":"Digital marketing agency based in Cuyahoga Falls, Ohio","technologies":[],"verified":true,"websiteUrl":"https://k6digital.com","yearFounded":1999}},{"node":{"alternateId":16765,"campaign":null,"clientBudget":4,"employeeRangeId":1,"id":"76dd5a8d-c73f-7397-2ee6-81ee95c63baa","industries":["Consumer Services","Information Services","Medical Practice"],"insights":{"projectCost":[{"docCount":13,"key":"total"},{"docCount":13,"key":"A"}],"projectMonthlyCost":[{"docCount":13,"key":"total"},{"docCount":1,"key":"A"},{"docCount":1,"key":"B"},{"docCount":2,"key":"Unspecified"},{"docCount":7,"key":"F"},{"docCount":1,"key":"C"},{"docCount":1,"key":"D"}],"reviewerCompanySize":[{"docCount":13,"key":"total"},{"docCount":10,"key":"Unspecified"},{"docCount":3,"key":"D"}],"reviewerIndustry":[{"docCount":9,"key":"total"},{"docCount":1,"key":"arts"},{"docCount":1,"key":"construction"},{"docCount":1,"key":"health"},{"docCount":2,"key":"hospitality"},{"docCount":1,"key":"it"},{"docCount":1,"key":"public"},{"docCount":1,"key":"real_estate"},{"docCount":1,"key":"transportation"}]},"logoUrl":"https://s3.amazonaws.com/top-local-agencies/profiles/logos/000/134/339/original/mv-circle-logo.png","name":"Mediavandals","physicalLocations":[{"city":"Port Hope","countryCode":"CA","id":"d741f1d1-2acc-4e3b-89fa-5584a6436ecd","state":"Ontario"}],"primaryLocation":{"city":"Port Hope","countryCode":"CA","id":"d741f1d1-2acc-4e3b-89fa-5584a6436ecd","state":"Ontario"},"projectBasedBudget":4,"reviewSummary":{"rating":{"rating":0.98},"totalCount":13},"services":[{"id":"digital-marketing","name":"Digital Marketing"},{"id":"seo","name":"SEO"},{"id":"web-design","name":"Web Design"}],"slug":"mediavandals","tagline":"Digital Marketing agency for dental businesses","technologies":[],"verified":true,"websiteUrl":"https://mediavandals.com","yearFounded":2010}}]